Workbook

Sheet Main_260329
A1: Class+Node [(Identifier (Key)] | B1: Class [Not chosen] | C1: Node [Not chosen] | D1: Required Mods [Not chosen] | E1: English [Source string] | F1: Korean (한국어) [Translation]
A2: AbilityDef+AM_AnalyzeCreature.label | B2: AbilityDef | C2: AM_AnalyzeCreature.label | E2: analyze creature | F2: 생물 분석
A3: AbilityDef+AM_AnalyzeCreature.description | B3: AbilityDef | C3: AM_AnalyzeCreature.description | E3: This ability allows the colonist to scan animals in the map and add them to a genetic database, receiving bonuses depending on the number of animals scanned.\n\nIt is very low range and some animals will move out of range constantly, so they can be downed first to make it easier.\n\nNote however that it won't work on dead animals, and it will also fail if no database has been built yet. | F3: 생물을 분석해 생물전서에 등록합니다. 분석한 생물의 종류에 따라 추가 효과를 받습니다.\n\n범위가 매우 좁고 분석 중인 생물이 범위 바깥으로 이동할 수도 있으므로, 생물을 먼저 쓰러트린 후 능력을 사용하는 것을 추천합니다.\n\n참고: 죽은 생물에게는 능력이 작동하지 않습니다. 아직 생물전서를 만들지 않은 경우에도 마찬가지입니다.
A4: AbilityDef+AM_ConvertStone.label | B4: AbilityDef | C4: AM_ConvertStone.label | E4: convert to pristine limestone | F4: 완벽한 석회암으로 변환
A5: AbilityDef+AM_ConvertStone.description | B5: AbilityDef | C5: AM_ConvertStone.description | E5: This ability allows the master architect to convert any stone block (for mod compatibility defined as anything with "Blocks" in its defName) to Pristine limestone, a stone that is both beautiful and damage resistant.\n\nTo do this, the architect uses... err... mechanites... or something... Look, I just wanted a new rock type to build pretty pyramids with, ok? | F5: 석재를 아름답고 손상에 강한 완벽한 석회암으로 변환합니다.
A6: AbilityDef+AM_FinishConstruction.label | B6: AbilityDef | C6: AM_FinishConstruction.label | E6: finish construction | F6: 완공
A7: AbilityDef+AM_FinishConstruction.description | B7: AbilityDef | C7: AM_FinishConstruction.description | E7: Once every 10 days the master architect can use this ability to finish the construction of a blueprint. | F7: 자원 운반이 완료된 청사진의 건설을 즉시 완료합니다.
A8: AbilityDef+AM_OcularConversion.label | B8: AbilityDef | C8: AM_OcularConversion.label | E8: ocular conversion | F8: 눈알 변환
A9: AbilityDef+AM_OcularConversion.description | B9: AbilityDef | C9: AM_OcularConversion.description | E9: Converts trees. | F9: 나무를 변환합니다.
A10: AbilityDef+AM_ChangeStyle.label | B10: AbilityDef | C10: AM_ChangeStyle.label | E10: change style | F10: 양식 변경
A11: AbilityDef+AM_ChangeStyle.description | B11: AbilityDef | C11: AM_ChangeStyle.description | E11: Change the styling of an item or building. Bear in mind that only the styles present in the colony's primary ideo can be used to swap (this can be changed in mod options to allow ALL possible styles). | F11: 물건이나 건물의 양식을 변경합니다.
A12: AbilityDef+AM_ChangeStyleRandom.label | B12: AbilityDef | C12: AM_ChangeStyleRandom.label | E12: change style, random | F12: 양식 변경 - 무작위
A13: AbilityDef+AM_ChangeStyleRandom.description | B13: AbilityDef | C13: AM_ChangeStyleRandom.description | E13: Change the styling of an item or building to a random supported style. Bear in mind that only the styles present in the colony's primary ideo can be used to swap (this can be changed in mod options to allow ALL possible styles). | F13: 물건이나 건물의 양식을 무작위로 변경합니다.
... A2567: ThoughtDef+AM_CorpseRumThought.stages.0.description | B2567: ThoughtDef | C2567: AM_CorpseRumThought.stages.0.description | E2567: The rum was so delicious, it allows me to reminisce fondly about our fallen comrades. | F2567: 럼주가 너무 맛있어서 쓰러진 전우들을 추억할 수 있어.
A2568: AbilityDef+AM_PsychicDeathKnell.label | B2568: AbilityDef | C2568: AM_PsychicDeathKnell.label | D2568: Royalty | E2568: psychic death knell | F2568: 죽음의 종소리
A2569: AbilityDef+AM_PsychicDeathKnell.description | B2569: AbilityDef | C2569: AM_PsychicDeathKnell.description | D2569: Royalty | E2569: Forcefully extract the latent psychic energy from a downed foe. Animals don't have enough intelligence to be of any use in this regard.\n\nIf the person casting the ability doesn't have psychic powers, they'll just receive a minor healing effect and a mood boost. If the person does have at least level 1 psychic powers this ability will recharge his or her focus, but will generate 30% of maximum psychic heat. | F2569: 쓰러져있는 적의 잠재된 정신 에너지를 강제로 뽑아냅니다. 동물은 이 능력의 대상이 될 정도의 지능을 가지고 있지 않습니다.\n\n이 능력을 시전하는 시전자가 초능력을 가지고 있지 않다면 약간의 회복 효과와 기분 보너스만 받습니다. 시전자가 1단계의 초능력이라도 가지고 있으면 이 능력은 시전자의 초집중을 재충전하지만, 신경열을 30% 증가시킵니다.
A2570: JobDef+AM_AnimaBurialLink.reportString | B2570: JobDef | C2570: AM_AnimaBurialLink.reportString | D2570: Royalty | E2570: linking TargetA. | F2570: {TargetA}(와)과 정신 연결 중
A2571: MemeDef+AM_PsychicVampirism.label | B2571: MemeDef | C2571: AM_PsychicVampirism.label | D2571: Royalty | E2571: psychic vampirism | F2571: 정신력 흡혈귀
A2572: MemeDef+AM_PsychicVampirism.description | B2572: MemeDef | C2572: AM_PsychicVampirism.description | D2572: Royalty | E2572: Meditation is useless and a waste of time. If we want to master the powers of the mind we will have to rip the psychic energy from the still pulsating brains of our enemies. | F2572: 명상은 쓸모없고 시간낭비다. 우리가 정신의 힘을 지배하고 싶다면 적들의 고통치는 뇌에서 정신력을 뜯어내야 한다.
A2573: MemeDef+AM_PsychicVampirism.generalRules.rulesStrings.0 | B2573: MemeDef | C2573: AM_PsychicVampirism.generalRules.rulesStrings.0 | D2573: Royalty | E2573: memeAdjective->draining | F2573: memeAdjective->흡수하는
A2574: MemeDef+AM_PsychicVampirism.generalRules.rulesStrings.1 | B2574: MemeDef | C2574: AM_PsychicVampirism.generalRules.rulesStrings.1 | D2574: Royalty | E2574: memeAdjective->psychic | F2574: memeAdjective->정신력
A2575: MemeDef+AM_PsychicVampirism.generalRules.rulesStrings.2 | B2575: MemeDef | C2575: AM_PsychicVampirism.generalRules.rulesStrings.2 | D2575: Royalty | E2575: memeHyphenPrefix->mind | F2575: memeHyphenPrefix->정신
A2576: MemeDef+AM_PsychicVampirism.generalRules.rulesStrings.3 | B2576: MemeDef | C2576: AM_PsychicVampirism.generalRules.rulesStrings.3 | D2576: Royalty | E2576: memeConcept->psychic draining | F2576: memeConcept->정신력 흡수
A2577: MemeDef+AM_PsychicVampirism.generalRules.rulesStrings.4 | B2577: MemeDef | C2577: AM_PsychicVampirism.generalRules.rulesStrings.4 | D2577: Royalty | E2577: memeLeaderNoun->thaumaturge | F2577: memeLeaderNoun->기적술사
A2578: MemeDef+AM_PsychicVampirism.generalRules.rulesStrings.5 | B2578: MemeDef | C2578: AM_PsychicVampirism.generalRules.rulesStrings.5 | D2578: Royalty | E2578: memeMoralist->sorcerer | F2578: memeMoralist->마법사
A2579: MemeDef+AM_PsychicVampirism.generalRules.rulesStrings.6 | B2579: MemeDef | C2579: AM_PsychicVampirism.generalRules.rulesStrings.6 | D2579: Royalty | E2579: memeMoralist->warlock | F2579: memeMoralist->주술사
... A3491: ThoughtDef+AM_TeaCeremonyTranscendent.stages.0.description | B3491: ThoughtDef | C3491: AM_TeaCeremonyTranscendent.stages.0.description | D3491: Vanilla Brewing Expanded | E3491: This ceremony was a profound experience, an unforgettable communion with the sacred tea. | F3491: 이 의식은 신성한 차와의 잊을 수 없는 교감, 심오한 경험이었어.
A3492: Keyed+AM_ArtTableExtraSpeed | B3492: Keyed | C3492: AM_ArtTableExtraSpeed | E3492: Art production speed: increased precept | F3492: 예술 작업 속도: 증가 규율
A3493: Keyed+AM_ExtraBluntArmorFactor | B3493: Keyed | C3493: AM_ExtraBluntArmorFactor | E3493: Armour: blunt precept | F3493: 갑옷: 둔탁함 규율
A3494: Keyed+AM_ExtraSharpArmorFactor | B3494: Keyed | C3494: AM_ExtraSharpArmorFactor | E3494: Armour: sharp precept | F3494: 갑옷: 날카로움 규율
A3495: Keyed+AM_ExtraHeatArmorFactor | B3495: Keyed | C3495: AM_ExtraHeatArmorFactor | E3495: Armour: heat precept | F3495: 갑옷: 열기 규율
A3496: Keyed+AM_MeditationFocusStrengthFactor | B3496: Keyed | C3496: AM_MeditationFocusStrengthFactor | E3496: Psyfocus gain: dampened precept | F3496: 초집중 획득: 약화
A3497: Keyed+AM_DespisedAnimals | B3497: Keyed | C3497: AM_DespisedAnimals | E3497: Despised Animals | F3497: 멸시받는 동물들
A3498: Keyed+AM_AddDespisedAnimals | B3498: Keyed | C3498: AM_AddDespisedAnimals | E3498: Despised Animal | F3498: 멸시받는 동물
A3499: Keyed+AM_AbilityNeedsADownedPawn | B3499: Keyed | C3499: AM_AbilityNeedsADownedPawn | E3499: This ability must target a downed sapient humanoid | F3499: 이 능력은 쓰러져있는 지성 있는 인간을 대상으로 해야합니다.
A3500: Keyed+AM_AbilityNeedsAValidAnimal | B3500: Keyed | C3500: AM_AbilityNeedsAValidAnimal | E3500: This ability must target a living, non-dryad animal | F3500: 이 능력은 살아있고, 나무지기가 아닌 동물을 대상으로 해야합니다.
A3501: Keyed+AM_AbilityNeedsABlueprint | B3501: Keyed | C3501: AM_AbilityNeedsABlueprint | E3501: This ability needs to target a building frame that is under construction | F3501: 이 능력은 건설 중인 청사진을 대상으로 해야 합니다.
A3502: Keyed+AM_AbilityNeedsResourcesDelivered | B3502: Keyed | C3502: AM_AbilityNeedsResourcesDelivered | E3502: All resources must have been delivered to the building frame | F3502: 모든 자원이 청사진에 전달되어야 합니다.
A3503: Keyed+AM_NoDataBaseFound | B3503: Keyed | C3503: AM_NoDataBaseFound | E3503: You'll need to build an animal database before this ability can be used | F3503: 이 능력을 사용하려면 먼저 생물전서를 건설해야 합니다.
... A3616: Keyed+AM_AllowHighImpactMemesForFluidIdeos_Tooltip | B3616: Keyed | C3616: AM_AllowHighImpactMemesForFluidIdeos_Tooltip | E3616: By default, fluid ideos only let you choose one meme with impact 1 or 2, blocking impact 3 memes from being chosen. With this option toggle you can make it so impact 3 memes are available too. | F3616: 기본적으로 유동적 사상에서는 영향력이 낮거나 보통인 가르침 하나만 선택할 수 있으며, 영향력이 높은 가르침은 선택할 수 없습니다. 이 옵션 토글을 사용하면 영향력이 높은 가르침도 사용할 수 있도록 설정할 수 있습니다.
A3617: Patches.TerrainDef+AB_Tile_OcularQuartz.label | B3617: Patches.TerrainDef | C3617: AB_Tile_OcularQuartz.label | D3617: Alpha Biomes | E3617: ocular red quartz floor | F3617: 눈알 장미 석영 바닥
A3618: Patches.TerrainDef+AB_Tile_OcularMudstone.label | B3618: Patches.TerrainDef | C3618: AB_Tile_OcularMudstone.label | D3618: Alpha Biomes | E3618: ocular mudstone floor | F3618: 눈알 이암 바닥
A3619: Patches.TerrainDef+AB_Tile_OcularCragstone.label | B3619: Patches.TerrainDef | C3619: AB_Tile_OcularCragstone.label | D3619: Alpha Biomes | E3619: ocular cragstone floor | F3619: 눈알 암석 바닥
A3620: Patches.TerrainDef+AB_Tile_OcularObsidian.label | B3620: Patches.TerrainDef | C3620: AB_Tile_OcularObsidian.label | D3620: Alpha Biomes | E3620: ocular obsidian floor | F3620: 눈알 흑요석 바닥
A3621: Patches.TerrainDef+AM_FinestonePristineLimestone.label | B3621: Patches.TerrainDef | C3621: AM_FinestonePristineLimestone.label | D3621: Royalty | E3621: fine pristine limestone tile | F3621: 멋진 완벽한 석회암 바닥
A3622: Patches.MemeDef+AM_GauranlenSupremacy.label | B3622: Patches.MemeDef | C3622: AM_GauranlenSupremacy.label | D3622: Vanilla Ideology Expanded - Anima Theme | E3622: dryad supremacy | F3622: 나무지기 지상주의
A3623: Patches.MemeDef+AM_GauranlenSupremacy.description | B3623: Patches.MemeDef | C3623: AM_GauranlenSupremacy.description | D3623: Vanilla Ideology Expanded - Anima Theme | E3623: The symbiotic relationship between humanity, anima nexus trees and their dryads is sacred. We will defend and nurture the trees, and in return they will help us protect our colony.\n\n<color=#E5E54C>Restrictions:</color>\n - This meme can only be chosen if the Tree Connection meme is chosen too (alternatively, the Biological Corruptors meme in Alpha Animals).\n\n<color=#E5E54C>Gameplay effect:</color>\n - Colony will start with three Unshackled dryads. | F3623: 인류와 요정나무, 그리고 나무의 나무지기 사이의 공생 관계는 신성하다. 우리는 나무를 지키고 보살필 것이다. 그러면 그 대가로 우리의 정착지를 보호하는 데 도움을 줄 것이다.\n\n&lt;color=#E5E54C&gt;제한:&lt;/color&gt;\n - 이 가르침은 수목주의 혹은 부패주의 가르침을 선택한 경우에만 선택할 수 있습니다.\n\n&lt;color=#E5E54C&gt;게임 플레이 효과:&lt;/color&gt;\n - 정착지는 묶여있지 않은 나무지기 셋과 함께 시작합니다.
A3624: Patches.ThingDef+AM_CubicCrib.label | B3624: Patches.ThingDef | C3624: AM_CubicCrib.label | D3624: Biotech && Anomaly | E3624: cubic crib | F3624: 큐브 아기 침대
A3625: Patches.ThingDef+AM_CubicCrib.description | B3625: Patches.ThingDef | C3625: AM_CubicCrib.description | D3625: Biotech && Anomaly | E3625: Let your babies rest in the loving embrace of the cube. A high quality crib will make a baby happy. Multiple cribs can be placed in a bedroom without turning it into a barracks. | F3625: 아기가 큐브의 사랑스러운 품에서 편안히 쉴 수 있도록 하세요. 높은 품질의 침대는 아기를 행복하게 해줍니다. 아기 침대는 한 방에 여러 개를 배치해도 방이 막사로 취급되지 않습니다.
A3626: Patches.PreceptDef+AM_HuntFocus_Strigoi.label | B3626: Patches.PreceptDef | C3626: AM_HuntFocus_Strigoi.label | D3626: Vanilla Races Expanded - Sanguophage && Biotech | E3626: strigoi | F3626: 스트리고이
A3627: Patches.PreceptDef+AM_HuntFocus_Strigoi.description | B3627: Patches.PreceptDef | C3627: AM_HuntFocus_Strigoi.description | D3627: Vanilla Races Expanded - Sanguophage && Biotech | E3627: Our purpose is clear: to seek out the cursed sanguophages wherever they may hide.\n\nStrigoi will be the focus of this precept.\n\n<color=#E5E54C>Gameplay effect:</color>\n - All attacks against a Strigoi will cause extra 10 burn damage. | F3627: 우리의 목적은 분명하다. 생귀오파지들이 어디에 숨어있던지 우린 찾아낼 것이다.\n\n스트리고이가 목표가 됩니다.\n\n<color=#E5E54C>게임 플레이 효과:</color>\n - 스트리고이에게 가하는 모든 공격이 추가로 화염 피해 10을 더 입힙니다.
A3628: Patches.PreceptDef+AM_HuntFocus_Ekkimian.label | B3628: Patches.PreceptDef | C3628: AM_HuntFocus_Ekkimian.label | D3628: Vanilla Races Expanded - Sanguophage && Biotech | E3628: ekkimian | F3628: 에키미안
... A3636: Patches.PreceptDef+AM_HuntFocus_Malachai.description | B3636: Patches.PreceptDef | C3636: AM_HuntFocus_Malachai.description | D3636: Vanilla Races Expanded - Sanguophage && Alpha Genes && Biotech | E3636: Our purpose is clear: to seek out the cursed sanguophages wherever they may hide.\n\nMalachai will be the focus of this precept.\n\n<color=#E5E54C>Gameplay effect:</color>\n - All attacks against a Malachai will cause extra 10 burn damage. | F3636: 우리의 목적은 분명하다. 생귀오파지들이 어디에 숨어있던지 우린 찾아낼 것이다.\n\n말라치이가 목표가 됩니다.\n\n<color=#E5E54C>게임 플레이 효과:</color>\n - 말라차이에게 가하는 모든 공격이 추가로 화염 피해 10을 더 입힙니다.
A3637: DamageDef+AM_HolyBurn.deathMessage | B3637: DamageDef | C3637: AM_HolyBurn.deathMessage | E3637: {0} has burned to death. | F3637: {0}(이)가 불타 죽었습니다.
A3638: VEF.OptionalFeatures.ModDef+AM_AlphaMemesIdeoMenuFeatures.label | B3638: VEF.OptionalFeatures.ModDef | C3638: AM_AlphaMemesIdeoMenuFeatures.label | E3638: Alpha Memes | F3638: 알파 밈
A3639: VEF.OptionalFeatures.ModDef+AM_AlphaMemesIdeoMenuFeatures.description | B3639: VEF.OptionalFeatures.ModDef | C3639: AM_AlphaMemesIdeoMenuFeatures.description | E3639: VE Framework new Ideo menu options for Alpha Memes | F3639: 알파 밈을 위한 새로운 이데올로기 옵션
A3640: ThingDef+AM_Star.label | B3640: ThingDef | C3640: AM_Star.label | E3640: Mote | F3640: Mote
A3641: ThingDef+AM_EyeOfHorus.label | B3641: ThingDef | C3641: AM_EyeOfHorus.label | E3641: Mote | F3641: Mote
A3642: ThingDef+AM_Obelisk.label | B3642: ThingDef | C3642: AM_Obelisk.label | E3642: Mote | F3642: Mote
A3643: ThingDef+AM_AtheismSymbol.label | B3643: ThingDef | C3643: AM_AtheismSymbol.label | E3643: Mote | F3643: Mote
A3644: ThingDef+AM_SikhSymbol.label | B3644: ThingDef | C3644: AM_SikhSymbol.label | E3644: Mote | F3644: Mote
A3645: ThingDef+AM_JainSpire.label | B3645: ThingDef | C3645: AM_JainSpire.label | E3645: Mote | F3645: Mote
A3646: ThingDef+AM_Cog.label | B3646: ThingDef | C3646: AM_Cog.label | E3646: Mote | F3646: Mote
A3647: ThingDef+AM_Skull.label | B3647: ThingDef | C3647: AM_Skull.label | E3647: Mote | F3647: Mote
A3648: ThingDef+AM_CavePaintings.label | B3648: ThingDef | C3648: AM_CavePaintings.label | E3648: Mote | F3648: Mote
... A3678: PreceptDef+AM_CremateFuneralNoCorpse.description | B3678: PreceptDef | C3678: AM_CremateFuneralNoCorpse.description | E3678: A gathering that occurs around a believer's grave after they die and are buried. If the body is destroyed, an empty grave can be used. Slaves don't get funerals. | F3678: 이 사상을 믿는 사람이 죽었을 때 치를 수 있는 행사입니다. 시신이 파괴됐다면 빈 무덤을 사용할 수도 있습니다. 노예는 장례식을 치를 수 없습니다.
A3679: ThingDef+AM_Hypercube.label | B3679: ThingDef | C3679: AM_Hypercube.label | D3679: Anomaly | E3679: Mote | F3679: Mote
A3680: ThingDef+AM_FleshRune.label | B3680: ThingDef | C3680: AM_FleshRune.label | D3680: Anomaly | E3680: Mote | F3680: Mote
A3681: ThingDef+AM_CultistRunes.label | B3681: ThingDef | C3681: AM_CultistRunes.label | D3681: Anomaly | E3681: Mote | F3681: Mote
A3682: ThingDef+AM_Building_Misc_FleshmassPiece1x1c.description | B3682: ThingDef | C3682: AM_Building_Misc_FleshmassPiece1x1c.description | D3682: Anomaly | E3682: A piece of fleshmass. | F3682: 뒤틀리고 단단한 살덩어리의 조각입니다.
A3683: ThingDef+AM_Building_Misc_FleshmassPiece1x1c.label | B3683: ThingDef | C3683: AM_Building_Misc_FleshmassPiece1x1c.label | D3683: Anomaly | E3683: fleshmass piece (1x1) | F3683: 살덩이 파편
A3684: ThingDef+AM_Building_Misc_FleshmassPiece2x2c.description | B3684: ThingDef | C3684: AM_Building_Misc_FleshmassPiece2x2c.description | D3684: Anomaly | E3684: A piece of fleshmass. | F3684: 뒤틀리고 단단한 살덩어리의 조각입니다.
A3685: ThingDef+AM_Building_Misc_FleshmassPiece2x2c.label | B3685: ThingDef | C3685: AM_Building_Misc_FleshmassPiece2x2c.label | D3685: Anomaly | E3685: fleshmass piece (2x2) | F3685: 큰 살덩이 파편
A3686: HistoryEventDef+AM_SanguophageCampRaided_DevPoints.label | B3686: HistoryEventDef | C3686: AM_SanguophageCampRaided_DevPoints.label | D3686: Biotech | E3686: raiding a sanguophage camp | F3686: 생귀오파지 캠프 습격
A3687: Patches.ThoughtDef+Catharsis.stages.1.label | B3687: Patches.ThoughtDef | C3687: Catharsis.stages.1.label | E3687: crazed catharsis | F3687: 미친 카타르시스
A3688: Patches.ThoughtDef+Catharsis.stages.1.description | B3688: Patches.ThoughtDef | C3688: Catharsis.stages.1.description | E3688: A flailing monkey wanted the TRUTH! A river a thousand paces wide would die for a grapefruit! | F3688: 몸부림치는 원숭이는 진실을 원했다! 천 걸음 넓이의 강은 자몽을 위해 죽을 것이다!

Sheet 250210
A1: Class+Node [(Identifier (Key)] | B1: Class [Not chosen] | C1: Node [Not chosen] | D1: Required Mods [Not chosen] | E1: English [Source string] | F1: Korean (한국어) [Translation]
A2: AbilityDef+AM_AnalyzeCreature.label | B2: AbilityDef | C2: AM_AnalyzeCreature.label | E2: analyze creature | F2: 생물 분석
A3: AbilityDef+AM_AnalyzeCreature.description | B3: AbilityDef | C3: AM_AnalyzeCreature.description | E3: This ability allows the colonist to scan animals in the map and add them to a genetic database, receiving bonuses depending on the number of animals scanned.\n\nIt is very low range and some animals will move out of range constantly, so they can be downed first to make it easier.\n\nNote however that it won't work on dead animals, and it will also fail if no database has been built yet. | F3: 생물을 분석해 생물전서에 등록합니다. 분석한 생물의 종류에 따라 추가 효과를 받습니다.\n\n범위가 매우 좁고 분석 중인 생물이 범위 바깥으로 이동할 수도 있으므로, 생물을 먼저 쓰러트린 후 능력을 사용하는 것을 추천합니다.\n\n참고: 죽은 생물에게는 능력이 작동하지 않습니다. 아직 생물전서를 만들지 않은 경우에도 마찬가지입니다.
A4: AbilityDef+AM_ConvertStone.label | B4: AbilityDef | C4: AM_ConvertStone.label | E4: convert to pristine limestone | F4: 완벽한 석회암으로 변환
A5: AbilityDef+AM_ConvertStone.description | B5: AbilityDef | C5: AM_ConvertStone.description | E5: This ability allows the master architect to convert any stone block (for mod compatibility defined as anything with "Blocks" in its defName) to Pristine limestone, a stone that is both beautiful and damage resistant.\n\nTo do this, the architect uses... err... mechanites... or something... Look, I just wanted a new rock type to build pretty pyramids with, ok? | F5: 석재를 아름답고 손상에 강한 완벽한 석회암으로 변환합니다.
A6: AbilityDef+AM_FinishConstruction.label | B6: AbilityDef | C6: AM_FinishConstruction.label | E6: finish construction | F6: 완공
A7: AbilityDef+AM_FinishConstruction.description | B7: AbilityDef | C7: AM_FinishConstruction.description | E7: Once every 10 days the master architect can use this ability to finish the construction of a blueprint. | F7: 자원 운반이 완료된 청사진의 건설을 즉시 완료합니다.
A8: AbilityDef+AM_OcularConversion.label | B8: AbilityDef | C8: AM_OcularConversion.label | E8: ocular conversion | F8: 눈알 변환
A9: AbilityDef+AM_OcularConversion.description | B9: AbilityDef | C9: AM_OcularConversion.description | E9: Converts trees. | F9: 나무를 변환합니다.
A10: AbilityDef+AM_ChangeStyle.label | B10: AbilityDef | C10: AM_ChangeStyle.label | E10: change style | F10: 양식 변경
A11: AbilityDef+AM_ChangeStyle.description | B11: AbilityDef | C11: AM_ChangeStyle.description | E11: Change the styling of an item or building. Bear in mind that only the styles present in the colony's primary ideo can be used to swap (this can be changed in mod options to allow ALL possible styles). | F11: 물건이나 건물의 양식을 변경합니다.
A12: AbilityDef+AM_ChangeStyleRandom.label | B12: AbilityDef | C12: AM_ChangeStyleRandom.label | E12: change style, random | F12: 양식 변경 - 무작위
A13: AbilityDef+AM_ChangeStyleRandom.description | B13: AbilityDef | C13: AM_ChangeStyleRandom.description | E13: Change the styling of an item or building to a random supported style. Bear in mind that only the styles present in the colony's primary ideo can be used to swap (this can be changed in mod options to allow ALL possible styles). | F13: 물건이나 건물의 양식을 무작위로 변경합니다.
... A2567: ThoughtDef+AM_CorpseRumThought.stages.0.description | B2567: ThoughtDef | C2567: AM_CorpseRumThought.stages.0.description | E2567: The rum was so delicious, it allows me to reminisce fondly about our fallen comrades. | F2567: 럼주가 너무 맛있어서 쓰러진 전우들을 추억할 수 있어.
A2568: AbilityDef+AM_PsychicDeathKnell.label | B2568: AbilityDef | C2568: AM_PsychicDeathKnell.label | D2568: Royalty | E2568: psychic death knell | F2568: 죽음의 종소리
A2569: AbilityDef+AM_PsychicDeathKnell.description | B2569: AbilityDef | C2569: AM_PsychicDeathKnell.description | D2569: Royalty | E2569: Forcefully extract the latent psychic energy from a downed foe. Animals don't have enough intelligence to be of any use in this regard.\n\nIf the person casting the ability doesn't have psychic powers, they'll just receive a minor healing effect and a mood boost. If the person does have at least level 1 psychic powers this ability will recharge his or her focus, but will generate 30% of maximum psychic heat. | F2569: 쓰러져있는 적의 잠재된 정신 에너지를 강제로 뽑아냅니다. 동물은 이 능력의 대상이 될 정도의 지능을 가지고 있지 않습니다.\n\n이 능력을 시전하는 시전자가 초능력을 가지고 있지 않다면 약간의 회복 효과와 기분 보너스만 받습니다. 시전자가 1단계의 초능력이라도 가지고 있으면 이 능력은 시전자의 초집중을 재충전하지만, 신경열을 30% 증가시킵니다.
A2570: JobDef+AM_AnimaBurialLink.reportString | B2570: JobDef | C2570: AM_AnimaBurialLink.reportString | D2570: Royalty | E2570: linking TargetA. | F2570: {TargetA}(와)과 정신 연결 중
A2571: MemeDef+AM_PsychicVampirism.label | B2571: MemeDef | C2571: AM_PsychicVampirism.label | D2571: Royalty | E2571: psychic vampirism | F2571: 정신력 흡혈귀
A2572: MemeDef+AM_PsychicVampirism.description | B2572: MemeDef | C2572: AM_PsychicVampirism.description | D2572: Royalty | E2572: Meditation is useless and a waste of time. If we want to master the powers of the mind we will have to rip the psychic energy from the still pulsating brains of our enemies. | F2572: 명상은 쓸모없고 시간낭비다. 우리가 정신의 힘을 지배하고 싶다면 적들의 고통치는 뇌에서 정신력을 뜯어내야 한다.
A2573: MemeDef+AM_PsychicVampirism.generalRules.rulesStrings.0 | B2573: MemeDef | C2573: AM_PsychicVampirism.generalRules.rulesStrings.0 | D2573: Royalty | E2573: memeAdjective->draining | F2573: memeAdjective->흡수하는
A2574: MemeDef+AM_PsychicVampirism.generalRules.rulesStrings.1 | B2574: MemeDef | C2574: AM_PsychicVampirism.generalRules.rulesStrings.1 | D2574: Royalty | E2574: memeAdjective->psychic | F2574: memeAdjective->정신력
A2575: MemeDef+AM_PsychicVampirism.generalRules.rulesStrings.2 | B2575: MemeDef | C2575: AM_PsychicVampirism.generalRules.rulesStrings.2 | D2575: Royalty | E2575: memeHyphenPrefix->mind | F2575: memeHyphenPrefix->정신
A2576: MemeDef+AM_PsychicVampirism.generalRules.rulesStrings.3 | B2576: MemeDef | C2576: AM_PsychicVampirism.generalRules.rulesStrings.3 | D2576: Royalty | E2576: memeConcept->psychic draining | F2576: memeConcept->정신력 흡수
A2577: MemeDef+AM_PsychicVampirism.generalRules.rulesStrings.4 | B2577: MemeDef | C2577: AM_PsychicVampirism.generalRules.rulesStrings.4 | D2577: Royalty | E2577: memeLeaderNoun->thaumaturge | F2577: memeLeaderNoun->기적술사
A2578: MemeDef+AM_PsychicVampirism.generalRules.rulesStrings.5 | B2578: MemeDef | C2578: AM_PsychicVampirism.generalRules.rulesStrings.5 | D2578: Royalty | E2578: memeMoralist->sorcerer | F2578: memeMoralist->마법사
A2579: MemeDef+AM_PsychicVampirism.generalRules.rulesStrings.6 | B2579: MemeDef | C2579: AM_PsychicVampirism.generalRules.rulesStrings.6 | D2579: Royalty | E2579: memeMoralist->warlock | F2579: memeMoralist->주술사
... A3491: ThoughtDef+AM_TeaCeremonyTranscendent.stages.0.description | B3491: ThoughtDef | C3491: AM_TeaCeremonyTranscendent.stages.0.description | D3491: Vanilla Brewing Expanded | E3491: This ceremony was a profound experience, an unforgettable communion with the sacred tea. | F3491: 이 의식은 신성한 차와의 잊을 수 없는 교감, 심오한 경험이었어.
A3492: Keyed+AM_ArtTableExtraSpeed | B3492: Keyed | C3492: AM_ArtTableExtraSpeed | E3492: Art production speed: increased precept | F3492: 예술 작업 속도: 증가 규율
A3493: Keyed+AM_ExtraBluntArmorFactor | B3493: Keyed | C3493: AM_ExtraBluntArmorFactor | E3493: Armour: blunt precept | F3493: 갑옷: 둔탁함 규율
A3494: Keyed+AM_ExtraSharpArmorFactor | B3494: Keyed | C3494: AM_ExtraSharpArmorFactor | E3494: Armour: sharp precept | F3494: 갑옷: 날카로움 규율
A3495: Keyed+AM_ExtraHeatArmorFactor | B3495: Keyed | C3495: AM_ExtraHeatArmorFactor | E3495: Armour: heat precept | F3495: 갑옷: 열기 규율
A3496: Keyed+AM_MeditationFocusStrengthFactor | B3496: Keyed | C3496: AM_MeditationFocusStrengthFactor | E3496: Psyfocus gain: dampened precept | F3496: 초집중 획득: 약화
A3497: Keyed+AM_DespisedAnimals | B3497: Keyed | C3497: AM_DespisedAnimals | E3497: Despised Animals | F3497: 멸시받는 동물들
A3498: Keyed+AM_AddDespisedAnimals | B3498: Keyed | C3498: AM_AddDespisedAnimals | E3498: Despised Animal | F3498: 멸시받는 동물
A3499: Keyed+AM_AbilityNeedsADownedPawn | B3499: Keyed | C3499: AM_AbilityNeedsADownedPawn | E3499: This ability must target a downed sapient humanoid | F3499: 이 능력은 쓰러져있는 지성 있는 인간을 대상으로 해야합니다.
A3500: Keyed+AM_AbilityNeedsAValidAnimal | B3500: Keyed | C3500: AM_AbilityNeedsAValidAnimal | E3500: This ability must target a living, non-dryad animal | F3500: 이 능력은 살아있고, 나무지기가 아닌 동물을 대상으로 해야합니다.
A3501: Keyed+AM_AbilityNeedsABlueprint | B3501: Keyed | C3501: AM_AbilityNeedsABlueprint | E3501: This ability needs to target a building frame that is under construction | F3501: 이 능력은 건설 중인 청사진을 대상으로 해야 합니다.
A3502: Keyed+AM_AbilityNeedsResourcesDelivered | B3502: Keyed | C3502: AM_AbilityNeedsResourcesDelivered | E3502: All resources must have been delivered to the building frame | F3502: 모든 자원이 청사진에 전달되어야 합니다.
A3503: Keyed+AM_NoDataBaseFound | B3503: Keyed | C3503: AM_NoDataBaseFound | E3503: You'll need to build an animal database before this ability can be used | F3503: 이 능력을 사용하려면 먼저 생물전서를 건설해야 합니다.
... A3616: Keyed+AM_AllowHighImpactMemesForFluidIdeos_Tooltip | B3616: Keyed | C3616: AM_AllowHighImpactMemesForFluidIdeos_Tooltip | E3616: By default, fluid ideos only let you choose one meme with impact 1 or 2, blocking impact 3 memes from being chosen. With this option toggle you can make it so impact 3 memes are available too. | F3616: 기본적으로 유동적 사상에서는 영향력이 낮거나 보통인 가르침 하나만 선택할 수 있으며, 영향력이 높은 가르침은 선택할 수 없습니다. 이 옵션 토글을 사용하면 영향력이 높은 가르침도 사용할 수 있도록 설정할 수 있습니다.
A3617: Patches.TerrainDef+AB_Tile_OcularQuartz.label | B3617: Patches.TerrainDef | C3617: AB_Tile_OcularQuartz.label | D3617: Alpha Biomes | E3617: ocular red quartz floor | F3617: 눈알 장미 석영 바닥
A3618: Patches.TerrainDef+AB_Tile_OcularMudstone.label | B3618: Patches.TerrainDef | C3618: AB_Tile_OcularMudstone.label | D3618: Alpha Biomes | E3618: ocular mudstone floor | F3618: 눈알 이암 바닥
A3619: Patches.TerrainDef+AB_Tile_OcularCragstone.label | B3619: Patches.TerrainDef | C3619: AB_Tile_OcularCragstone.label | D3619: Alpha Biomes | E3619: ocular cragstone floor | F3619: 눈알 암석 바닥
A3620: Patches.TerrainDef+AB_Tile_OcularObsidian.label | B3620: Patches.TerrainDef | C3620: AB_Tile_OcularObsidian.label | D3620: Alpha Biomes | E3620: ocular obsidian floor | F3620: 눈알 흑요석 바닥
A3621: Patches.TerrainDef+AM_FinestonePristineLimestone.label | B3621: Patches.TerrainDef | C3621: AM_FinestonePristineLimestone.label | D3621: Royalty | E3621: fine pristine limestone tile | F3621: 멋진 완벽한 석회암 바닥
A3622: Patches.MemeDef+AM_GauranlenSupremacy.label | B3622: Patches.MemeDef | C3622: AM_GauranlenSupremacy.label | D3622: Vanilla Ideology Expanded - Anima Theme | E3622: dryad supremacy | F3622: 나무지기 지상주의
A3623: Patches.MemeDef+AM_GauranlenSupremacy.description | B3623: Patches.MemeDef | C3623: AM_GauranlenSupremacy.description | D3623: Vanilla Ideology Expanded - Anima Theme | E3623: The symbiotic relationship between humanity, anima nexus trees and their dryads is sacred. We will defend and nurture the trees, and in return they will help us protect our colony.\n\n<color=#E5E54C>Restrictions:</color>\n - This meme can only be chosen if the Tree Connection meme is chosen too (alternatively, the Biological Corruptors meme in Alpha Animals).\n\n<color=#E5E54C>Gameplay effect:</color>\n - Colony will start with three Unshackled dryads. | F3623: 인류와 요정나무, 그리고 나무의 나무지기 사이의 공생 관계는 신성하다. 우리는 나무를 지키고 보살필 것이다. 그러면 그 대가로 우리의 정착지를 보호하는 데 도움을 줄 것이다.\n\n&lt;color=#E5E54C&gt;제한:&lt;/color&gt;\n - 이 가르침은 수목주의 혹은 부패주의 가르침을 선택한 경우에만 선택할 수 있습니다.\n\n&lt;color=#E5E54C&gt;게임 플레이 효과:&lt;/color&gt;\n - 정착지는 묶여있지 않은 나무지기 셋과 함께 시작합니다.
A3624: Patches.ThingDef+AM_CubicCrib.label | B3624: Patches.ThingDef | C3624: AM_CubicCrib.label | D3624: Biotech && Anomaly | E3624: cubic crib | F3624: 큐브 아기 침대
A3625: Patches.ThingDef+AM_CubicCrib.description | B3625: Patches.ThingDef | C3625: AM_CubicCrib.description | D3625: Biotech && Anomaly | E3625: Let your babies rest in the loving embrace of the cube. A high quality crib will make a baby happy. Multiple cribs can be placed in a bedroom without turning it into a barracks. | F3625: 아기가 큐브의 사랑스러운 품에서 편안히 쉴 수 있도록 하세요. 높은 품질의 침대는 아기를 행복하게 해줍니다. 아기 침대는 한 방에 여러 개를 배치해도 방이 막사로 취급되지 않습니다.
A3626: Patches.PreceptDef+AM_HuntFocus_Strigoi.label | B3626: Patches.PreceptDef | C3626: AM_HuntFocus_Strigoi.label | D3626: Vanilla Races Expanded - Sanguophage && Biotech | E3626: strigoi | F3626: 스트리고이
A3627: Patches.PreceptDef+AM_HuntFocus_Strigoi.description | B3627: Patches.PreceptDef | C3627: AM_HuntFocus_Strigoi.description | D3627: Vanilla Races Expanded - Sanguophage && Biotech | E3627: Our purpose is clear: to seek out the cursed sanguophages wherever they may hide.\n\nStrigoi will be the focus of this precept.\n\n<color=#E5E54C>Gameplay effect:</color>\n - All attacks against a Strigoi will cause extra 10 burn damage. | F3627: 우리의 목적은 분명하다. 생귀오파지들이 어디에 숨어있던지 우린 찾아낼 것이다.\n\n스트리고이가 목표가 됩니다.\n\n<color=#E5E54C>게임 플레이 효과:</color>\n - 스트리고이에게 가하는 모든 공격이 추가로 화염 피해 10을 더 입힙니다.
A3628: Patches.PreceptDef+AM_HuntFocus_Ekkimian.label | B3628: Patches.PreceptDef | C3628: AM_HuntFocus_Ekkimian.label | D3628: Vanilla Races Expanded - Sanguophage && Biotech | E3628: ekkimian | F3628: 에키미안
... A3636: Patches.PreceptDef+AM_HuntFocus_Malachai.description | B3636: Patches.PreceptDef | C3636: AM_HuntFocus_Malachai.description | D3636: Vanilla Races Expanded - Sanguophage && Alpha Genes && Biotech | E3636: Our purpose is clear: to seek out the cursed sanguophages wherever they may hide.\n\nMalachai will be the focus of this precept.\n\n<color=#E5E54C>Gameplay effect:</color>\n - All attacks against a Malachai will cause extra 10 burn damage. | F3636: 우리의 목적은 분명하다. 생귀오파지들이 어디에 숨어있던지 우린 찾아낼 것이다.\n\n말라치이가 목표가 됩니다.\n\n<color=#E5E54C>게임 플레이 효과:</color>\n - 말라차이에게 가하는 모든 공격이 추가로 화염 피해 10을 더 입힙니다.
A3637: DamageDef+AM_HolyBurn.deathMessage | B3637: DamageDef | C3637: AM_HolyBurn.deathMessage | E3637: {0} has burned to death. | F3637: {0}(이)가 불타 죽었습니다.
A3638: VEF.OptionalFeatures.ModDef+AM_AlphaMemesIdeoMenuFeatures.label | B3638: VEF.OptionalFeatures.ModDef | C3638: AM_AlphaMemesIdeoMenuFeatures.label | E3638: Alpha Memes | F3638: 알파 밈
A3639: VEF.OptionalFeatures.ModDef+AM_AlphaMemesIdeoMenuFeatures.description | B3639: VEF.OptionalFeatures.ModDef | C3639: AM_AlphaMemesIdeoMenuFeatures.description | E3639: VE Framework new Ideo menu options for Alpha Memes | F3639: 알파 밈을 위한 새로운 이데올로기 옵션
A3640: ThingDef+AM_Star.label | B3640: ThingDef | C3640: AM_Star.label | E3640: Mote | F3640: Mote
A3641: ThingDef+AM_EyeOfHorus.label | B3641: ThingDef | C3641: AM_EyeOfHorus.label | E3641: Mote | F3641: Mote
A3642: ThingDef+AM_Obelisk.label | B3642: ThingDef | C3642: AM_Obelisk.label | E3642: Mote | F3642: Mote
A3643: ThingDef+AM_AtheismSymbol.label | B3643: ThingDef | C3643: AM_AtheismSymbol.label | E3643: Mote | F3643: Mote
A3644: ThingDef+AM_SikhSymbol.label | B3644: ThingDef | C3644: AM_SikhSymbol.label | E3644: Mote | F3644: Mote
A3645: ThingDef+AM_JainSpire.label | B3645: ThingDef | C3645: AM_JainSpire.label | E3645: Mote | F3645: Mote
A3646: ThingDef+AM_Cog.label | B3646: ThingDef | C3646: AM_Cog.label | E3646: Mote | F3646: Mote
A3647: ThingDef+AM_Skull.label | B3647: ThingDef | C3647: AM_Skull.label | E3647: Mote | F3647: Mote
A3648: ThingDef+AM_CavePaintings.label | B3648: ThingDef | C3648: AM_CavePaintings.label | E3648: Mote | F3648: Mote
... A3678: PreceptDef+AM_CremateFuneralNoCorpse.description | B3678: PreceptDef | C3678: AM_CremateFuneralNoCorpse.description | E3678: A gathering that occurs around a believer's grave after they die and are buried. If the body is destroyed, an empty grave can be used. Slaves don't get funerals. | F3678: 이 사상을 믿는 사람이 죽었을 때 치를 수 있는 행사입니다. 시신이 파괴됐다면 빈 무덤을 사용할 수도 있습니다. 노예는 장례식을 치를 수 없습니다.
A3679: ThingDef+AM_Hypercube.label | B3679: ThingDef | C3679: AM_Hypercube.label | D3679: Anomaly | E3679: Mote | F3679: Mote
A3680: ThingDef+AM_FleshRune.label | B3680: ThingDef | C3680: AM_FleshRune.label | D3680: Anomaly | E3680: Mote | F3680: Mote
A3681: ThingDef+AM_CultistRunes.label | B3681: ThingDef | C3681: AM_CultistRunes.label | D3681: Anomaly | E3681: Mote | F3681: Mote
A3682: ThingDef+AM_Building_Misc_FleshmassPiece1x1c.description | B3682: ThingDef | C3682: AM_Building_Misc_FleshmassPiece1x1c.description | D3682: Anomaly | E3682: A piece of fleshmass. | F3682: 뒤틀리고 단단한 살덩어리의 조각입니다.
A3683: ThingDef+AM_Building_Misc_FleshmassPiece1x1c.label | B3683: ThingDef | C3683: AM_Building_Misc_FleshmassPiece1x1c.label | D3683: Anomaly | E3683: fleshmass piece (1x1) | F3683: 살덩이 파편
A3684: ThingDef+AM_Building_Misc_FleshmassPiece2x2c.description | B3684: ThingDef | C3684: AM_Building_Misc_FleshmassPiece2x2c.description | D3684: Anomaly | E3684: A piece of fleshmass. | F3684: 뒤틀리고 단단한 살덩어리의 조각입니다.
A3685: ThingDef+AM_Building_Misc_FleshmassPiece2x2c.label | B3685: ThingDef | C3685: AM_Building_Misc_FleshmassPiece2x2c.label | D3685: Anomaly | E3685: fleshmass piece (2x2) | F3685: 큰 살덩이 파편
A3686: HistoryEventDef+AM_SanguophageCampRaided_DevPoints.label | B3686: HistoryEventDef | C3686: AM_SanguophageCampRaided_DevPoints.label | D3686: Biotech | E3686: raiding a sanguophage camp | F3686: 생귀오파지 캠프 습격
A3687: Patches.ThoughtDef+Catharsis.stages.1.label | B3687: Patches.ThoughtDef | C3687: Catharsis.stages.1.label | E3687: crazed catharsis | F3687: 미친 카타르시스
A3688: Patches.ThoughtDef+Catharsis.stages.1.description | B3688: Patches.ThoughtDef | C3688: Catharsis.stages.1.description | E3688: A flailing monkey wanted the TRUTH! A river a thousand paces wide would die for a grapefruit! | F3688: 몸부림치는 원숭이는 진실을 원했다! 천 걸음 넓이의 강은 자몽을 위해 죽을 것이다!

Sheet 240721
A1: Class+Node [(Identifier (Key)] | B1: Class [Not chosen] | C1: Node [Not chosen] | D1: Required Mods [Not chosen] | E1: English [Source string] | F1: Korean (한국어) [Translation]
A2: AbilityDef+AM_AnalyzeCreature.label | B2: AbilityDef | C2: AM_AnalyzeCreature.label | E2: analyze creature | F2: 생물 분석
A3: AbilityDef+AM_AnalyzeCreature.description | B3: AbilityDef | C3: AM_AnalyzeCreature.description | E3: This ability allows the colonist to scan animals in the map and add them to a genetic database, receiving bonuses depending on the number of animals scanned.\n\nIt is very low range and some animals will move out of range constantly, so they can be downed first to make it easier.\n\nNote however that it won't work on dead animals, and it will also fail if no database has been built yet. | F3: 이 능력은 정착민이 지도에서 생물을 분석해 생물 데이터베이스에 추가하여 분석한 생물의 수에 따라 보너스를 받을 수 있게 합니다.\n\n이 능력은 범위가 매우 작고 어떤 생물들은 지속적으로 범위 밖으로 이동하기 때문에 생물을 먼저 쓰러트리고 능력을 쉽게 사용할 수도 있습니다.\n\n참고: 죽은 생물에게는 능력이 작동하지 않으며 아직 데이터베이스를 만들지 않은 경우에도 마찬가지입니다.
A4: AbilityDef+AM_ConvertStone.label | B4: AbilityDef | C4: AM_ConvertStone.label | E4: convert to pristine limestone | F4: 완벽한 석회암으로 변환
A5: AbilityDef+AM_ConvertStone.description | B5: AbilityDef | C5: AM_ConvertStone.description | E5: This ability allows the master architect to convert any stone block (for mod compatibility defined as anything with "Blocks" in its defName) to Pristine limestone, a stone that is both beautiful and damage resistant.\n\nTo do this, the architect uses... err... mechanites... or something... Look, I just wanted a new rock type to build pretty pyramids with, ok? | F5: 이 능력은 건축 장인이 다른 석재(모드 호환성을 위해 defName 에 "Blocks"으로 정의된 것)를 아름답고 손상에 강한 완벽한 석회암 석재로 변환시킵니다.\n\n이걸 사용해서 건축가는... 어... 메카나이트... 뭐 그런거... 난 그냥 예쁜 피라미드를 지을 수 있는 새로운 암석 종류를 원했을 뿐이야. 알겠어?
A6: AbilityDef+AM_FinishConstruction.label | B6: AbilityDef | C6: AM_FinishConstruction.label | E6: finish construction | F6: 완공
A7: AbilityDef+AM_FinishConstruction.description | B7: AbilityDef | C7: AM_FinishConstruction.description | E7: Once every 10 days the master architect can use this ability to finish the construction of a blueprint. | F7: 10일마다 한번, 건축 장인이 이 능력을 사용하여 자원 운반이 완료된 청사진의 건설을 즉시 완료할 수 있습니다.
A8: AbilityDef+AM_OcularConversion.label | B8: AbilityDef | C8: AM_OcularConversion.label | E8: ocular conversion | F8: 눈알 변환
A9: AbilityDef+AM_OcularConversion.description | B9: AbilityDef | C9: AM_OcularConversion.description | E9: Converts trees. | F9: 나무를 변환합니다.
A10: AbilityDef+AM_ChangeStyle.label | B10: AbilityDef | C10: AM_ChangeStyle.label | E10: change style | F10: 양식 변경
A11: AbilityDef+AM_ChangeStyle.description | B11: AbilityDef | C11: AM_ChangeStyle.description | E11: Change the styling of an item or building. Bear in mind that only the styles present in the colony's primary ideo can be used to swap (this can be changed in mod options to allow ALL possible styles). | F11: 정착지의 지도자가 이 능력으로 물건이나 건물의 양식을 바꿀 수 있습니다. 정착지의 기본 사상에 들어있는 양식 범주로만 변경할 수 있습니다. (모드 설정에서 가능한 모든 양식을 허용하도록 변경할 수 있습니다.)
A12: AbilityDef+AM_ChangeStyleRandom.label | B12: AbilityDef | C12: AM_ChangeStyleRandom.label | E12: change style, random | F12: 양식 변경 - 무작위
A13: AbilityDef+AM_ChangeStyleRandom.description | B13: AbilityDef | C13: AM_ChangeStyleRandom.description | E13: Change the styling of an item or building to a random supported style. Bear in mind that only the styles present in the colony's primary ideo can be used to swap (this can be changed in mod options to allow ALL possible styles). | F13: 아이템 또는 건물의 양식을 무작위로 변경합니다. 정착지의 이념에 맞는 양식으로만 변경됩니다. (모드 옵션에서 모든 양식을 허용하도록 변경할 수 있습니다)
... A232: MemeDef+AM_BiologicalDefilers.descriptionMaker.rules.rulesStrings.21 | B232: MemeDef | C232: AM_BiologicalDefilers.descriptionMaker.rules.rulesStrings.21 | E232: alienistProphecy(tag=meme_BiologicalDefilers)->We must destroy these lifeforms, for humanity has gone way too far. All the galaxy is being remade in the image of our original planet, and that is obscene. | F232: alienistProphecy(tag=meme_BiologicalDefilers)->우리는 이 생명체들을 파괴해야 한다. 인류는 너무 멀리 갔다. 은하계 전체가 우리의 원래 행성의 이미지로 재창조되고 있으며, 이는 혐오스럽다.
A233: MemeDef+AM_GauranlenSupremacy.label | B233: MemeDef | C233: AM_GauranlenSupremacy.label | E233: gauranlen supremacy | G233: 요정나무 지상주의 | H233: Vanilla Ideology Expanded - Anima Theme의 로드 유무에 따라 분기되어 패치로 해야함.
A234: MemeDef+AM_GauranlenSupremacy.description | B234: MemeDef | C234: AM_GauranlenSupremacy.description | E234: The symbiotic relationship between humanity, gauranlen trees and their dryads is sacred. We will defend and nurture the trees, and in return they will help us protect our colony.\n\n<color=#E5E54C>Restrictions:</color>\n - This meme can only be chosen if the Tree Connection meme is chosen too (alternatively, the Biological Corruptors meme in Alpha Animals).\n\n<color=#E5E54C>Gameplay effect:</color>\n - Colony will start with three Unshackled dryads. | G234: 인류와 요정나무, 그리고 나무의 나무지기 사이의 공생 관계는 신성하다. 우리는 나무를 지키고 보살필 것이다. 그러면 그 대가로 우리의 정착지를 보호하는 데 도움을 줄 것이다.\n\n<color=#E5E54C>제한:</color>\n - 이 가르침은 수목주의 혹은 부패주의 가르침을 선택한 경우에만 선택할 수 있습니다.\n\n<color=#E5E54C>게임 플레이 효과:</color>\n - 정착지는 묶여있지 않은 나무지기 셋과 함께 시작합니다. | H234: Vanilla Ideology Expanded - Anima Theme의 로드 유무에 따라 분기되어 패치로 해야함.
A235: MemeDef+AM_GauranlenSupremacy.generalRules.rulesStrings.0 | B235: MemeDef | C235: AM_GauranlenSupremacy.generalRules.rulesStrings.0 | E235: memeCreed->dryad | F235: memeCreed->나무지기
A236: MemeDef+AM_GauranlenSupremacy.generalRules.rulesStrings.1 | B236: MemeDef | C236: AM_GauranlenSupremacy.generalRules.rulesStrings.1 | E236: memeCreed->gauranlen tree | F236: memeCreed->요정나무
A237: MemeDef+AM_GauranlenSupremacy.generalRules.rulesStrings.2 | B237: MemeDef | C237: AM_GauranlenSupremacy.generalRules.rulesStrings.2 | E237: memeConcept->gauranlen trees | F237: memeConcept->요정나무들
A238: MemeDef+AM_GauranlenSupremacy.generalRules.rulesStrings.3 | B238: MemeDef | C238: AM_GauranlenSupremacy.generalRules.rulesStrings.3 | E238: memeConcept->dryads | F238: memeConcept->나무지기들
A239: MemeDef+AM_GauranlenSupremacy.generalRules.rulesStrings.4 | B239: MemeDef | C239: AM_GauranlenSupremacy.generalRules.rulesStrings.4 | E239: memeAdjective->druidic | F239: memeAdjective->드루이드의
A240: MemeDef+AM_GauranlenSupremacy.generalRules.rulesStrings.5 | B240: MemeDef | C240: AM_GauranlenSupremacy.generalRules.rulesStrings.5 | E240: memeAdjective->barky | F240: memeAdjective->나무껍질의
A241: MemeDef+AM_GauranlenSupremacy.generalRules.rulesStrings.6 | B241: MemeDef | C241: AM_GauranlenSupremacy.generalRules.rulesStrings.6 | E241: memeHyphenPrefix->tree | F241: memeHyphenPrefix->나무
A242: MemeDef+AM_GauranlenSupremacy.generalRules.rulesStrings.7 | B242: MemeDef | C242: AM_GauranlenSupremacy.generalRules.rulesStrings.7 | E242: memeHyphenPrefix->arbor | F242: memeHyphenPrefix->수목
A243: MemeDef+AM_GauranlenSupremacy.generalRules.rulesStrings.8 | B243: MemeDef | C243: AM_GauranlenSupremacy.generalRules.rulesStrings.8 | E243: memeHyphenPrefix->dryad | F243: memeHyphenPrefix->나무지기
A244: MemeDef+AM_GauranlenSupremacy.generalRules.rulesStrings.9 | B244: MemeDef | C244: AM_GauranlenSupremacy.generalRules.rulesStrings.9 | E244: memeLeaderNoun->dryadkeeper | F244: memeLeaderNoun->나무지기 수호자
A245: MemeDef+AM_GauranlenSupremacy.generalRules.rulesStrings.10 | B245: MemeDef | C245: AM_GauranlenSupremacy.generalRules.rulesStrings.10 | E245: memeLeaderNoun->arborist | F245: memeLeaderNoun->수목 재배자
A246: MemeDef+AM_GauranlenSupremacy.generalRules.rulesStrings.11 | B246: MemeDef | C246: AM_GauranlenSupremacy.generalRules.rulesStrings.11 | E246: memeLeaderAdjective->green | F246: memeLeaderAdjective->녹색의
... A1413: TerrainDef+AM_Tile_Futuristic_Kemetic.description | B1413: TerrainDef | C1413: AM_Tile_Futuristic_Kemetic.description | E1413: Fine steel plates with a hexagonal pattern for that ultra-technological look. | F1413: 극도로 기술적인 외형을 위해 육각형 무늬를 새긴 고급 철판입니다.
A1414: TerrainDef+AM_TilePristineLimestone.description | B1414: TerrainDef | C1414: AM_TilePristineLimestone.description | E1414: Carefully-cut and fit stone tiles for a castle feeling. They are pretty to look at, but they take a long time to lay.
A1415: TerrainDef+AM_TilePristineLimestone.label | B1415: TerrainDef | C1415: AM_TilePristineLimestone.label | E1415: pristine limestone tile | F1415: 완벽한 석회암 바닥
A1416: TerrainDef+AM_FlagstonePristineLimestone.description | B1416: TerrainDef | C1416: AM_FlagstonePristineLimestone.description | E1416: Roughly-cut stone tiles. These are not beautiful, but they make good surfaces for roads and outdoor walkways. Deconstructing flagstone yields no resources.
A1417: TerrainDef+AM_FlagstonePristineLimestone.label | B1417: TerrainDef | C1417: AM_FlagstonePristineLimestone.label | E1417: pristine limestone flagstone | F1417: 완벽한 석회암 판석
A1418: DesignatorDropdownGroupDef+AM_Floor_SteampunkTiles.label | B1418: DesignatorDropdownGroupDef | C1418: AM_Floor_SteampunkTiles.label | E1418: steampunk stone tiles | F1418: 스팀펑크 바닥
A1419: TerrainDef+AM_SteampunkTileSandstone.description | B1419: TerrainDef | C1419: AM_SteampunkTileSandstone.description | E1419: Carefully-cut and fit stone tiles in a Steampunk style. They are pretty to look at, but they take a long time to lay. | F1419: 스팀펑크 양식 돌 바닥입니다. 조심스럽게 깎고 다듬어 예쁘지만 시간이 오래 걸립니다.
A1420: TerrainDef+AM_SteampunkTileSandstone.label | B1420: TerrainDef | C1420: AM_SteampunkTileSandstone.label | E1420: steampunk sandstone tile | F1420: 스팀펑크 사암 바닥
A1421: TerrainDef+AM_SteampunkTileGranite.description | B1421: TerrainDef | C1421: AM_SteampunkTileGranite.description | E1421: Carefully-cut and fit stone tiles in a Steampunk style. They are pretty to look at, but they take a long time to lay. | F1421: 스팀펑크 양식 돌 바닥입니다. 조심스럽게 깎고 다듬어 예쁘지만 시간이 오래 걸립니다.
A1422: TerrainDef+AM_SteampunkTileGranite.label | B1422: TerrainDef | C1422: AM_SteampunkTileGranite.label | E1422: steampunk granite tile | F1422: 스팀펑크 화강암 바닥
A1423: TerrainDef+AM_SteampunkTileLimestone.description | B1423: TerrainDef | C1423: AM_SteampunkTileLimestone.description | E1423: Carefully-cut and fit stone tiles in a Steampunk style. They are pretty to look at, but they take a long time to lay. | F1423: 스팀펑크 양식 돌 바닥입니다. 조심스럽게 깎고 다듬어 예쁘지만 시간이 오래 걸립니다.
A1424: TerrainDef+AM_SteampunkTileLimestone.label | B1424: TerrainDef | C1424: AM_SteampunkTileLimestone.label | E1424: steampunk limestone tile | F1424: 스팀펑크 석회암 바닥
A1425: TerrainDef+AM_SteampunkTileSlate.description | B1425: TerrainDef | C1425: AM_SteampunkTileSlate.description | E1425: Carefully-cut and fit stone tiles in a Steampunk style. They are pretty to look at, but they take a long time to lay. | F1425: 스팀펑크 양식 돌 바닥입니다. 조심스럽게 깎고 다듬어 예쁘지만 시간이 오래 걸립니다.
A1426: TerrainDef+AM_SteampunkTileSlate.label | B1426: TerrainDef | C1426: AM_SteampunkTileSlate.label | E1426: steampunk slate tile | F1426: 스팀펑크 점판암 바닥
A1427: TerrainDef+AM_SteampunkTileMarble.description | B1427: TerrainDef | C1427: AM_SteampunkTileMarble.description | E1427: Carefully-cut and fit stone tiles in a Steampunk style. They are pretty to look at, but they take a long time to lay. | F1427: 스팀펑크 양식 돌 바닥입니다. 조심스럽게 깎고 다듬어 예쁘지만 시간이 오래 걸립니다.
A1428: TerrainDef+AM_SteampunkTileMarble.label | B1428: TerrainDef | C1428: AM_SteampunkTileMarble.label | E1428: steampunk marble tile | F1428: 스팀펑크 대리석 바닥
... A1876: PreceptDef+AM_BlastOffFuneral.description | B1876: PreceptDef | C1876: AM_BlastOffFuneral.description | E1876: A gathering to witness our friend be sent off to the stars. | F1876: 별들에게 보내지는 우리들의 친구를 보기 위한 모임입니다.
A1877: PreceptDef+AM_BlastOffFuneral.extraTextPawnDeathLetter | B1877: PreceptDef | C1877: AM_BlastOffFuneral.extraTextPawnDeathLetter | E1877: {PAWN_nameDef} should be loaded into a transport pod and blasted off, so {PAWN_possessive} friends and family can move on.
A1878: PreceptDef+AM_CremateFuneral.label | B1878: PreceptDef | C1878: AM_CremateFuneral.label | E1878: cremation funeral | F1878: 화장 장례식
A1879: PreceptDef+AM_CremateFuneral.description | B1879: PreceptDef | C1879: AM_CremateFuneral.description | E1879: A gathering to witness the cremation of our friend. | F1879: 화장되는 우리들의 친구를 보기 위한 모임입니다.
A1880: PreceptDef+AM_CremateFuneral.extraTextPawnDeathLetter | B1880: PreceptDef | C1880: AM_CremateFuneral.extraTextPawnDeathLetter | E1880: {PAWN_nameDef} should be cremated and their dust scattered so {PAWN_possessive} friends and family can move on.
A1881: PreceptDef+AM_CremateFuneralNoCorpse.description | B1881: PreceptDef | C1881: AM_CremateFuneralNoCorpse.description | E1881: A gathering that occurs around a believer's grave after they die and are buried. If the body is destroyed, an empty grave can be used. Slaves don't get funerals.
A1882: PreceptDef+AM_CremateFuneralNoCorpse.label | B1882: PreceptDef | C1882: AM_CremateFuneralNoCorpse.label | E1882: funeral (no corpse) | F1882: 장례식 (시신 없음)
A1883: PreceptDef+AM_InsectoidBurial.label | B1883: PreceptDef | C1883: AM_InsectoidBurial.label | E1883: hive burial | F1883: 곤충 군락 장례식
A1884: PreceptDef+AM_InsectoidBurial.description | B1884: PreceptDef | C1884: AM_InsectoidBurial.description | E1884: A gathering to witness our friend offered to the greater powers; Insects! | F1884: 강력한 존재들인 곤충에게 제공되는 우리들의 친구를 보기 위한 모임입니다.
A1885: PreceptDef+AM_InsectoidBurial.extraTextPawnDeathLetter | B1885: PreceptDef | C1885: AM_InsectoidBurial.extraTextPawnDeathLetter | E1885: {PAWN_nameDef} should be offered to the insectoids so {PAWN_possessive} friends and family will know they are with the superior race
A1886: PreceptDef+AM_Mummification.label | B1886: PreceptDef | C1886: AM_Mummification.label | E1886: mummification funeral | F1886: 미라화 장례식
A1887: PreceptDef+AM_Mummification.description | B1887: PreceptDef | C1887: AM_Mummification.description | E1887: A gathering to witness the mummification of our friend | F1887: 미라가 되는 우리들의 친구를 보기 위한 모임입니다.
A1888: PreceptDef+AM_Mummification.extraTextPawnDeathLetter | B1888: PreceptDef | C1888: AM_Mummification.extraTextPawnDeathLetter | E1888: {PAWN_nameDef} should be mummmified so {PAWN_possessive} friends and family can visit them whenever they want.
A1889: PreceptDef+AM_FuneralNoCorpse.label | B1889: PreceptDef | C1889: AM_FuneralNoCorpse.label | E1889: funeral (no corpse) | F1889: 장례식 (시신 없음)
A1890: PreceptDef+AM_FuneralNoCorpse.description | B1890: PreceptDef | C1890: AM_FuneralNoCorpse.description | E1890: A gathering to witness the cremation of our friend. | F1890: 이 사상을 믿는 사람이 죽었을 때 치를 수 있는 행사입니다. 시신이 파괴됐다면 빈 무덤을 사용할 수도 있습니다. 노예는 장례식을 치를 수 없습니다.
A1891: PreceptDef+AM_OcularFuneral.label | B1891: PreceptDef | C1891: AM_OcularFuneral.label | E1891: ocular funeral | F1891: 눈알 장례식
A1892: PreceptDef+AM_OcularFuneral.description | B1892: PreceptDef | C1892: AM_OcularFuneral.description | E1892: A gathering to witness the deceased be offered to the ocular lands! | F1892: 고인의 넋을 눈알 숲에 바치는 모임입니다.
A1893: PreceptDef+AM_OcularFuneral.extraTextPawnDeathLetter | B1893: PreceptDef | C1893: AM_OcularFuneral.extraTextPawnDeathLetter | E1893: {PAWN_nameDef} should be offered to the ocular lands, so it may reward us with wonderous creatures
A1894: PreceptDef+AM_PastedFuneral.label | B1894: PreceptDef | C1894: AM_PastedFuneral.label | E1894: nutrient paste funeral | F1894: 영양죽 장례식
A1895: PreceptDef+AM_PastedFuneral.description | B1895: PreceptDef | C1895: AM_PastedFuneral.description | E1895: A gathering to ensure nothing goes to waste | F1895: 낭비되는 것이 없도록 하기 위한 모임입니다.
A1896: PreceptDef+AM_PastedFuneral.extraTextPawnDeathLetter | B1896: PreceptDef | C1896: AM_PastedFuneral.extraTextPawnDeathLetter | E1896: {PAWN_nameDef} should be turned into paste. It's what they'd want.
A1897: PreceptDef+AM_PyramidBurial.label | B1897: PreceptDef | C1897: AM_PyramidBurial.label | E1897: pyramid burial funeral | F1897: 피라미드 매장 장례식
A1898: PreceptDef+AM_PyramidBurial.description | B1898: PreceptDef | C1898: AM_PyramidBurial.description | E1898: A gathering to entomb our colleague within a subterranean burial chamber underneath a pyramid | F1898: 피라미드 아래 지하 묘실에 동료를 매장하기 위한 모임입니다.
A1899: PreceptDef+AM_PyramidBurial.extraTextPawnDeathLetter | B1899: PreceptDef | C1899: AM_PyramidBurial.extraTextPawnDeathLetter | E1899: {PAWN_nameDef} should be entombed so {PAWN_pronoun} can watch us all from the afterlife.
A1900: PreceptDef+AM_RumBurial.label | B1900: PreceptDef | C1900: AM_RumBurial.label | E1900: rum burial | F1900: 럼주 매장
A1901: PreceptDef+AM_RumBurial.description | B1901: PreceptDef | C1901: AM_RumBurial.description | E1901: A gathering to turn our friends into delicious rum. | F1901: 친구들을 맛있는 럼주로 만들기 위한 모임입니다.
A1902: PreceptDef+AM_RumBurial.extraTextPawnDeathLetter | B1902: PreceptDef | C1902: AM_RumBurial.extraTextPawnDeathLetter | E1902: {PAWN_nameDef} should be placed in a rum vat so {PAWN_possessive} friends and family can enjoy their sweet rum.
A1903: PreceptDef+AM_SkyBurial.label | B1903: PreceptDef | C1903: AM_SkyBurial.label | E1903: sky burial | F1903: 풍장 장례식
A1904: PreceptDef+AM_SkyBurial.description | B1904: PreceptDef | C1904: AM_SkyBurial.description | E1904: A gathering to witness the send off of our friend to nature. | F1904: 자연에게 보내지는 우리들의 친구를 보기 위한 모임입니다.
A1905: PreceptDef+AM_SkyBurial.extraTextPawnDeathLetter | B1905: PreceptDef | C1905: AM_SkyBurial.extraTextPawnDeathLetter | E1905: {PAWN_nameDef} should be left in a secluded area and left to nature so {PAWN_possessive} friends and family can move on as their.
A1906: RitualPatternDef+AM_BlastOffFuneralPattern.ritualExpectedDesc | B1906: RitualPatternDef | C1906: AM_BlastOffFuneralPattern.ritualExpectedDesc | E1906: Once a {IDEO} member dies, other {MEMBERS} witness their friend return to space. | F1906: {IDEO} 구성원이 죽으면, 다른 {MEMBERS}들은 그들의 친구가 우주로 돌아가는 것을 봅니다.
A1907: RitualBehaviorDef+AM_BlastOffBehavior.spectatorFilter.description | B1907: RitualBehaviorDef | C1907: AM_BlastOffBehavior.spectatorFilter.description | E1907: Spectators must be alive. | F1907: 관전자는 살아있어야 합니다.
A1908: RitualBehaviorDef+AM_BlastOffBehavior.roles.0.label | B1908: RitualBehaviorDef | C1908: AM_BlastOffBehavior.roles.0.label | E1908: speaker | F1908: 연설자
A1909: RitualBehaviorDef+AM_BlastOffBehavior.roles.1.label | B1909: RitualBehaviorDef | C1909: AM_BlastOffBehavior.roles.1.label | E1909: Corpse | F1909: 시체
A1910: RitualBehaviorDef+AM_BlastOffBehavior.stages.1.postAction.text | B1910: RitualBehaviorDef | C1910: AM_BlastOffBehavior.stages.1.postAction.text | E1910: {0}: The speech is over, the shuttle is blasting off! | F1910: {0}: 연설이 끝났습니다. 수송 포드가 발사됩니다!
A1911: RitualOutcomeEffectDef+AM_BlastOffFuneralOutcome.description | B1911: RitualOutcomeEffectDef | C1911: AM_BlastOffFuneralOutcome.description | E1911: Depending on ritual quality, participants will get between {MINMOOD} and {MAXMOOD} mood for {MOODDAYS} days. | F1911: 의식의 품질에 따라, 참여자들은 {MINMOOD}~{MAXMOOD} 기분을 {MOODDAYS}일 동안 얻게 됩니다.
A1912: RitualOutcomeEffectDef+AM_BlastOffFuneralOutcome.outcomeChances.0.label | B1912: RitualOutcomeEffectDef | C1912: AM_BlastOffFuneralOutcome.outcomeChances.0.label | E1912: Terrible | F1912: 끔찍한
A1913: RitualOutcomeEffectDef+AM_BlastOffFuneralOutcome.outcomeChances.0.description | B1913: RitualOutcomeEffectDef | C1913: AM_BlastOffFuneralOutcome.outcomeChances.0.description | E1913: The {0} was terrible! They came back down on a nearby settlement who are now furious. | F1913: {0}(은)는 끔찍했습니다! 수송 포드는 지금 분노하고 있는 인근 정착지로 다시 내려왔습니다.
A1914: RitualOutcomeEffectDef+AM_BlastOffFuneralOutcome.outcomeChances.1.label | B1914: RitualOutcomeEffectDef | C1914: AM_BlastOffFuneralOutcome.outcomeChances.1.label | E1914: Lackluster | F1914: 흐리멍탕한
A1915: RitualOutcomeEffectDef+AM_BlastOffFuneralOutcome.outcomeChances.1.description | B1915: RitualOutcomeEffectDef | C1915: AM_BlastOffFuneralOutcome.outcomeChances.1.description | E1915: The {0} was lackluster. We think they didn't even reach the atmosphere! Some swear they saw them come back down. | F1915: {0}(은)는 흐리멍텅했습니다. 수송 포드가 대기권에 도달하지도 않았다고 생각됩니다! 어떤 이들은 그것들이 다시 내려오는 것을 봤다고 말하고 있습니다.
A1916: RitualOutcomeEffectDef+AM_BlastOffFuneralOutcome.outcomeChances.2.label | B1916: RitualOutcomeEffectDef | C1916: AM_BlastOffFuneralOutcome.outcomeChances.2.label | E1916: Good | F1916: 좋은
A1917: RitualOutcomeEffectDef+AM_BlastOffFuneralOutcome.outcomeChances.2.description | B1917: RitualOutcomeEffectDef | C1917: AM_BlastOffFuneralOutcome.outcomeChances.2.description | E1917: The {0} was good. The speaker's final words were satisfying, and the smell of chemfuel was the perfect sendoff. | F1917: {0}(은)는 좋았습니다. 연설의 마지막 구절은 만족스러웠고, 화학 연료 냄새는 완벽한 배웅이였습니다.
... A1921: RitualOutcomeEffectDef+AM_BlastOffFuneralOutcome.comps.1.label | B1921: RitualOutcomeEffectDef | C1921: AM_BlastOffFuneralOutcome.comps.1.label | E1921: participant count | F1921: 참여자 수
A1922: RitualOutcomeEffectDef+AM_BlastOffFuneralOutcome.modExtensions.0.worstOutcomeDesc | B1922: RitualOutcomeEffectDef | C1922: AM_BlastOffFuneralOutcome.modExtensions.0.worstOutcomeDesc | E1922: The {RITUAL} was a disaster! Not only did {CORPSE} not reach the stars, they landed in {SETTLEMENT} causing a diplomatic disaster!
A1923: RitualOutcomeEffectDef+AM_BlastOffFuneralOutcome.modExtensions.0.bestOutcomeDesc | B1923: RitualOutcomeEffectDef | C1923: AM_BlastOffFuneralOutcome.modExtensions.0.bestOutcomeDesc | E1923: The {RITUAL} spectacular! {CORPSE} has reached the stars, which led a trade ship to come investigate!
A1924: RitualPatternDef+AM_CremateFuneralPattern.ritualExpectedDesc | B1924: RitualPatternDef | C1924: AM_CremateFuneralPattern.ritualExpectedDesc | E1924: Once a {IDEO} member dies, other {MEMBERS} witnesss {RITUAL_labelDef} return to dust. | F1924: {IDEO} 구성원이 죽으면, 다른 {MEMBERS}들은 {RITUAL_labelDef}(으)로 재로 돌아가는 것을 봅니다.
A1925: RitualBehaviorDef+AM_CremateFuneralBehavior.spectatorFilter.description | B1925: RitualBehaviorDef | C1925: AM_CremateFuneralBehavior.spectatorFilter.description | E1925: Spectators must be alive. | F1925: 관전자는 살아있어야 합니다.
A1926: RitualBehaviorDef+AM_CremateFuneralBehavior.roles.0.label | B1926: RitualBehaviorDef | C1926: AM_CremateFuneralBehavior.roles.0.label | E1926: speaker | F1926: 연설자
A1927: RitualBehaviorDef+AM_CremateFuneralBehavior.roles.1.label | B1927: RitualBehaviorDef | C1927: AM_CremateFuneralBehavior.roles.1.label | E1927: Corpse | F1927: 시체
A1928: RitualBehaviorDef+AM_CremateFuneralBehavior.roles.2.label | B1928: RitualBehaviorDef | C1928: AM_CremateFuneralBehavior.roles.2.label | E1928: crafter | F1928: 예술가
A1929: RitualBehaviorDef+AM_CremateFuneralBehavior.stages.1.postAction.text | B1929: RitualBehaviorDef | C1929: AM_CremateFuneralBehavior.stages.1.postAction.text | E1929: {0}: The speech is over, and the cremation is beginning. | F1929: {0}: 연설이 끝났습니다. 화장이 시작됩니다.
A1930: RitualBehaviorDef+AM_CremateFuneralBehavior.stages.0.failTriggers.0.desc | B1930: RitualBehaviorDef | C1930: AM_CremateFuneralBehavior.stages.0.failTriggers.0.desc | E1930: Selected stuff is not reachable | F1930: 선택한 재료에 도달할 수 없습니다.
A1931: RitualOutcomeEffectDef+AM_CremateFuneralOutcome.description | B1931: RitualOutcomeEffectDef | C1931: AM_CremateFuneralOutcome.description | E1931: Depending on ritual quality, participants will get between {MINMOOD} and {MAXMOOD} mood for {MOODDAYS} days. | F1931: 의식의 품질에 따라, 참여자들은 {MINMOOD}~{MAXMOOD} 기분을 {MOODDAYS}일 동안 얻게 됩니다.
A1932: RitualOutcomeEffectDef+AM_CremateFuneralOutcome.outcomeChances.0.label | B1932: RitualOutcomeEffectDef | C1932: AM_CremateFuneralOutcome.outcomeChances.0.label | E1932: Terrible | F1932: 끔찍한
A1933: RitualOutcomeEffectDef+AM_CremateFuneralOutcome.outcomeChances.0.description | B1933: RitualOutcomeEffectDef | C1933: AM_CremateFuneralOutcome.outcomeChances.0.description | E1933: The {0} was terrible! The speech was boring and the crematorium wasn't hot enough. | F1933: {0}(은)는 끔찍했습니다! 연설은 지루했고 화장터는 충분히 뜨겁지 않았습니다.
A1934: RitualOutcomeEffectDef+AM_CremateFuneralOutcome.outcomeChances.1.label | B1934: RitualOutcomeEffectDef | C1934: AM_CremateFuneralOutcome.outcomeChances.1.label | E1934: Lackluster | F1934: 흐리멍탕한
...

Sheet Sheet1 (2)
A1: Class+Node [(Identifier (Key)] | B1: Class [Not chosen] | C1: Required Mods [Not chosen] | D1: English [Source string] | G1: Korean (한국어) [Translation]
A2: AbilityDef+AM_AnalyzeCreature.label | B2: AbilityDef | D2: analyze creature | F2: =IF(E2="",IF(C2="",A2,C2),E2) -> AbilityDef+AM_AnalyzeCreature.label | G2: 생물 분석 | H2: =IF(ISERROR(E2),"",MATCH(F2,'240721'!$A$2:$A$2763,0)) -> 1
A3: AbilityDef+AM_AnalyzeCreature.description | B3: AbilityDef | D3: This ability allows the colonist to scan animals in the map and add them to a genetic database, receiving bonuses depending on the number of animals scanned.\n\nIt is very low range and some animals will move out of range constantly, so they can be downed first to make it easier.\n\nNote however that it won't work on dead animals, and it will also fail if no database has been built yet. | F3: =IF(E3="",IF(C3="",A3,C3),E3) -> AbilityDef+AM_AnalyzeCreature.description | G3: 이 능력은 정착민이 지도에서 생물을 분석해 생물 데이터베이스에 추가하여 분석한 생물의 수에 따라 보너스를 받을 수 있게 합니다.\n\n이 능력은 범위가 매우 작고 어떤 생물들은 지속적으로 범위 밖으로 이동하기 때문에 생물을 먼저 쓰러트리고 능력을 쉽게 사용할 수도 있습니다.\n\n참고: 죽은 생물에게는 능력이 작동하지 않으며 아직 데이터베이스를 만들지 않은 경우에도 마찬가지입니다. | H3: =IF(ISERROR(E3),"",MATCH(F3,'240721'!$A$2:$A$2763,0)) -> 2
A4: AbilityDef+AM_ConvertStone.label | B4: AbilityDef | D4: convert to pristine limestone | F4: =IF(E4="",IF(C4="",A4,C4),E4) -> AbilityDef+AM_ConvertStone.label | G4: 완벽한 석회암으로 변환 | H4: =IF(ISERROR(E4),"",MATCH(F4,'240721'!$A$2:$A$2763,0)) -> 3
A5: AbilityDef+AM_ConvertStone.description | B5: AbilityDef | D5: This ability allows the master architect to convert any stone block (for mod compatibility defined as anything with "Blocks" in its defName) to Pristine limestone, a stone that is both beautiful and damage resistant.\n\nTo do this, the architect uses... err... mechanites... or something... Look, I just wanted a new rock type to build pretty pyramids with, ok? | F5: =IF(E5="",IF(C5="",A5,C5),E5) -> AbilityDef+AM_ConvertStone.description | G5: 이 능력은 건축 장인이 다른 석재(모드 호환성을 위해 defName 에 "Blocks"으로 정의된 것)를 아름답고 손상에 강한 완벽한 석회암 석재로 변환시킵니다.\n\n이걸 사용해서 건축가는... 어... 메카나이트... 뭐 그런거... 난 그냥 예쁜 피라미드를 지을 수 있는 새로운 암석 종류를 원했을 뿐이야. 알겠어? | H5: =IF(ISERROR(E5),"",MATCH(F5,'240721'!$A$2:$A$2763,0)) -> 4
A6: AbilityDef+AM_FinishConstruction.label | B6: AbilityDef | D6: finish construction | F6: =IF(E6="",IF(C6="",A6,C6),E6) -> AbilityDef+AM_FinishConstruction.label | G6: 완공 | H6: =IF(ISERROR(E6),"",MATCH(F6,'240721'!$A$2:$A$2763,0)) -> 5
A7: AbilityDef+AM_FinishConstruction.description | B7: AbilityDef | D7: Once every 10 days the master architect can use this ability to finish the construction of a blueprint. | F7: =IF(E7="",IF(C7="",A7,C7),E7) -> AbilityDef+AM_FinishConstruction.description | G7: 10일마다 한번, 건축 장인이 이 능력을 사용하여 자원 운반이 완료된 청사진의 건설을 즉시 완료할 수 있습니다. | H7: =IF(ISERROR(E7),"",MATCH(F7,'240721'!$A$2:$A$2763,0)) -> 6
A8: AbilityDef+AM_ChangeStyle.label | B8: AbilityDef | D8: change style | F8: =IF(E8="",IF(C8="",A8,C8),E8) -> AbilityDef+AM_ChangeStyle.label | G8: 양식 변경 | H8: =IF(ISERROR(E8),"",MATCH(F8,'240721'!$A$2:$A$2763,0)) -> 9
A9: AbilityDef+AM_ChangeStyle.description | B9: AbilityDef | D9: Change the styling of an item or building. Bear in mind that only the styles present in the colony's primary ideo can be used to swap (this can be changed in mod options to allow ALL possible styles). | F9: =IF(E9="",IF(C9="",A9,C9),E9) -> AbilityDef+AM_ChangeStyle.description | G9: 정착지의 지도자가 이 능력으로 물건이나 건물의 양식을 바꿀 수 있습니다. 정착지의 기본 사상에 들어있는 양식 범주로만 변경할 수 있습니다. (모드 설정에서 가능한 모든 양식을 허용하도록 변경할 수 있습니다.) | H9: =IF(ISERROR(E9),"",MATCH(F9,'240721'!$A$2:$A$2763,0)) -> 10
A10: AbilityDef+AM_PsychicDeathKnell.label | B10: AbilityDef | D10: psychic death knell | F10: =IF(E10="",IF(C10="",A10,C10),E10) -> AbilityDef+AM_PsychicDeathKnell.label | G10: 죽음의 종소리 | H10: =IF(ISERROR(E10),"",MATCH(F10,'240721'!$A$2:$A$2763,0)) -> 2151
A11: AbilityDef+AM_PsychicDeathKnell.description | B11: AbilityDef | D11: Forcefully extract the latent psychic energy from a downed foe. Animals don't have enough intelligence to be of any use in this regard.\n\nIf the person casting the ability doesn't have psychic powers, they'll just receive a minor healing effect and a mood boost. If the person does have at least level 1 psychic powers this ability will recharge his or her focus, but will generate 30% of maximum psychic heat. | F11: =IF(E11="",IF(C11="",A11,C11),E11) -> AbilityDef+AM_PsychicDeathKnell.description | G11: 쓰러져있는 적의 잠재된 정신 에너지를 강제로 뽑아냅니다. 동물은 이 능력의 대상이 될 정도의 지능을 가지고 있지 않습니다.\n\n이 능력을 시전하는 시전자가 초능력을 가지고 있지 않다면 약간의 회복 효과와 기분 보너스만 받습니다. 시전자가 1단계의 초능력이라도 가지고 있으면 이 능력은 시전자의 초집중을 재충전하지만, 신경열을 30% 증가시킵니다. | H11: =IF(ISERROR(E11),"",MATCH(F11,'240721'!$A$2:$A$2763,0)) -> 2152
A12: AbilityDef+AM_OcularConversion.label | B12: AbilityDef | D12: ocular conversion | F12: =IF(E12="",IF(C12="",A12,C12),E12) -> AbilityDef+AM_OcularConversion.label | G12: 눈알 변환 | H12: =IF(ISERROR(E12),"",MATCH(F12,'240721'!$A$2:$A$2763,0)) -> 7
A13: AbilityDef+AM_OcularConversion.description | B13: AbilityDef | D13: Converts trees. | F13: =IF(E13="",IF(C13="",A13,C13),E13) -> AbilityDef+AM_OcularConversion.description | G13: 나무를 변환합니다. | H13: =IF(ISERROR(E13),"",MATCH(F13,'240721'!$A$2:$A$2763,0)) -> 8
... A22: BodyDef+AM_EyeBody.label | B22: BodyDef | D22: eye | F22: =IF(E22="",IF(C22="",A22,C22),E22) -> BodyDef+AM_EyeBody.label | G22: 눈 | H22: =IF(ISERROR(E22),"",MATCH(F22,'240721'!$A$2:$A$2763,0)) -> 19
A23: BodyDef+AM_EyeBody.corePart.parts.0.customLabel | B23: BodyDef | D23: stomach pouch | E23: BodyDef+AM_EyeBody.corePart.parts.stomach_pouch.customLabel | F23: =IF(E23="",IF(C23="",A23,C23),E23) -> BodyDef+AM_EyeBody.corePart.parts.stomach_pouch.customLabel | G23: 위 주머니 | H23: =IF(ISERROR(E23),"",MATCH(F23,'240721'!$A$2:$A$2763,0)) -> 20
A24: BodyDef+AM_EyeBody.corePart.parts.1.customLabel | B24: BodyDef | D24: gastrovascular cavity | E24: BodyDef+AM_EyeBody.corePart.parts.gastrovascular_cavity.customLabel | F24: =IF(E24="",IF(C24="",A24,C24),E24) -> BodyDef+AM_EyeBody.corePart.parts.gastrovascular_cavity.customLabel | G24: 위혈관 | H24: =IF(ISERROR(E24),"",MATCH(F24,'240721'!$A$2:$A$2763,0)) -> 21
A25: BodyDef+AM_EyeBody.corePart.parts.3.customLabel | B25: BodyDef | D25: first tentacle | E25: BodyDef+AM_EyeBody.corePart.parts.first_tentacle.customLabel | F25: =IF(E25="",IF(C25="",A25,C25),E25) -> BodyDef+AM_EyeBody.corePart.parts.first_tentacle.customLabel | G25: 첫 번째 촉수 | H25: =IF(ISERROR(E25),"",MATCH(F25,'240721'!$A$2:$A$2763,0)) -> 22
A26: BodyDef+AM_EyeBody.corePart.parts.4.customLabel | B26: BodyDef | D26: second tentacle | E26: BodyDef+AM_EyeBody.corePart.parts.second_tentacle.customLabel | F26: =IF(E26="",IF(C26="",A26,C26),E26) -> BodyDef+AM_EyeBody.corePart.parts.second_tentacle.customLabel | G26: 두 번째 촉수 | H26: =IF(ISERROR(E26),"",MATCH(F26,'240721'!$A$2:$A$2763,0)) -> 23
A27: BodyDef+AM_EyeBody.corePart.parts.5.customLabel | B27: BodyDef | D27: third tentacle | E27: BodyDef+AM_EyeBody.corePart.parts.third_tentacle.customLabel | F27: =IF(E27="",IF(C27="",A27,C27),E27) -> BodyDef+AM_EyeBody.corePart.parts.third_tentacle.customLabel | G27: 세 번째 촉수 | H27: =IF(ISERROR(E27),"",MATCH(F27,'240721'!$A$2:$A$2763,0)) -> 24
A28: BodyDef+AM_EyeBody.corePart.parts.2.parts.0.customLabel | B28: BodyDef | D28: eye | E28: BodyDef+AM_EyeBody.corePart.parts.2.parts.eye.customLabel | F28: =IF(E28="",IF(C28="",A28,C28),E28) -> BodyDef+AM_EyeBody.corePart.parts.2.parts.eye.customLabel | G28: 눈 | H28: =IF(ISERROR(E28),"",MATCH(F28,'240721'!$A$2:$A$2763,0)) -> 25
A29: BodyPartDef+AM_JellyfishTentacle.label | B29: BodyPartDef | D29: tentacle | F29: =IF(E29="",IF(C29="",A29,C29),E29) -> BodyPartDef+AM_JellyfishTentacle.label | G29: 촉수 | H29: =IF(ISERROR(E29),"",MATCH(F29,'240721'!$A$2:$A$2763,0)) -> 36
A30: BodyPartDef+AM_EyeBody.label | B30: BodyPartDef | D30: eye | F30: =IF(E30="",IF(C30="",A30,C30),E30) -> BodyPartDef+AM_EyeBody.label | G30: 눈 | H30: =IF(ISERROR(E30),"",MATCH(F30,'240721'!$A$2:$A$2763,0)) -> 37
A31: BodyPartGroupDef+AA_Body.label | B31: BodyPartGroupDef | D31: body | F31: =IF(E31="",IF(C31="",A31,C31),E31) -> BodyPartGroupDef+AA_Body.label | G31: 몸 | H31: =IF(ISERROR(E31),"",MATCH(F31,'240721'!$A$2:$A$2763,0)) -> 26
A32: BodyPartGroupDef+AA_Mouth.label | B32: BodyPartGroupDef | D32: mouth | F32: =IF(E32="",IF(C32="",A32,C32),E32) -> BodyPartGroupDef+AA_Mouth.label | G32: 입 | H32: =IF(ISERROR(E32),"",MATCH(F32,'240721'!$A$2:$A$2763,0)) -> 27
A33: BodyPartGroupDef+AA_Sting.label | B33: BodyPartGroupDef | D33: stinger | F33: =IF(E33="",IF(C33="",A33,C33),E33) -> BodyPartGroupDef+AA_Sting.label | G33: 침 | H33: =IF(ISERROR(E33),"",MATCH(F33,'240721'!$A$2:$A$2763,0)) -> 28
A34: BodyPartGroupDef+AA_PincerAttackTool.label | B34: BodyPartGroupDef | D34: pincer | F34: =IF(E34="",IF(C34="",A34,C34),E34) -> BodyPartGroupDef+AA_PincerAttackTool.label | G34: 집게 | H34: =IF(ISERROR(E34),"",MATCH(F34,'240721'!$A$2:$A$2763,0)) -> 29
A35: BodyPartGroupDef+AA_BladeAttackTool.label | B35: BodyPartGroupDef | D35: blade | F35: =IF(E35="",IF(C35="",A35,C35),E35) -> BodyPartGroupDef+AA_BladeAttackTool.label | G35: 칼날 | H35: =IF(ISERROR(E35),"",MATCH(F35,'240721'!$A$2:$A$2763,0)) -> 30
A36: BodyPartGroupDef+AA_TentacleAttackTool.label | B36: BodyPartGroupDef | D36: tentacle | F36: =IF(E36="",IF(C36="",A36,C36),E36) -> BodyPartGroupDef+AA_TentacleAttackTool.label | G36: 촉수 | H36: =IF(ISERROR(E36),"",MATCH(F36,'240721'!$A$2:$A$2763,0)) -> 31
A37: BodyPartGroupDef+AA_EyestalkAttackTool.label | B37: BodyPartGroupDef | D37: eyestalk | F37: =IF(E37="",IF(C37="",A37,C37),E37) -> BodyPartGroupDef+AA_EyestalkAttackTool.label | G37: 눈자루 | H37: =IF(ISERROR(E37),"",MATCH(F37,'240721'!$A$2:$A$2763,0)) -> 32
A38: BodyPartGroupDef+LegAttackTool.label | B38: BodyPartGroupDef | D38: leg | F38: =IF(E38="",IF(C38="",A38,C38),E38) -> BodyPartGroupDef+LegAttackTool.label | G38: 다리 | H38: =IF(ISERROR(E38),"",MATCH(F38,'240721'!$A$2:$A$2763,0)) -> 33
A39: BodyPartGroupDef+TuskAttackTool.label | B39: BodyPartGroupDef | D39: tusk | F39: =IF(E39="",IF(C39="",A39,C39),E39) -> BodyPartGroupDef+TuskAttackTool.label | G39: 엄니 | H39: =IF(ISERROR(E39),"",MATCH(F39,'240721'!$A$2:$A$2763,0)) -> 34
A40: BodyPartGroupDef+AA_Tail.label | B40: BodyPartGroupDef | D40: tail | F40: =IF(E40="",IF(C40="",A40,C40),E40) -> BodyPartGroupDef+AA_Tail.label | G40: 꼬리 | H40: =IF(ISERROR(E40),"",MATCH(F40,'240721'!$A$2:$A$2763,0)) -> 35
... A79: HediffDef+AM_ToxicBuildup.label | B79: HediffDef | D79: toxic buildup | F79: =IF(E79="",IF(C79="",A79,C79),E79) -> HediffDef+AM_ToxicBuildup.label | G79: 중독 | H79: =IF(ISERROR(E79),"",MATCH(F79,'240721'!$A$2:$A$2763,0)) -> 67
A80: HediffDef+AM_ToxicBuildup.stages.0.label | B80: HediffDef | D80: initial | E80: =NA() -> #N/A | F80: =IF(E80="",IF(C80="",A80,C80),E80) -> #N/A | G80: 초기 | H80: =IF(ISERROR(E80),"",MATCH(F80,'240721'!$A$2:$A$2763,0))
A81: HediffDef+AM_ToxicBuildup.stages.1.label | B81: HediffDef | D81: initial | E81: HediffDef+AM_ToxicBuildup.stages.initial.label | F81: =IF(E81="",IF(C81="",A81,C81),E81) -> HediffDef+AM_ToxicBuildup.stages.initial.label | G81: 초기 | H81: =IF(ISERROR(E81),"",MATCH(F81,'240721'!$A$2:$A$2763,0)) -> 68
A82: HediffDef+AM_ToxicBuildup.stages.2.label | B82: HediffDef | D82: minor | E82: HediffDef+AM_ToxicBuildup.stages.minor.label | F82: =IF(E82="",IF(C82="",A82,C82),E82) -> HediffDef+AM_ToxicBuildup.stages.minor.label | G82: 가벼움 | H82: =IF(ISERROR(E82),"",MATCH(F82,'240721'!$A$2:$A$2763,0)) -> 69
A83: HediffDef+AM_ToxicBuildup.stages.3.label | B83: HediffDef | D83: moderate | E83: HediffDef+AM_ToxicBuildup.stages.moderate.label | F83: =IF(E83="",IF(C83="",A83,C83),E83) -> HediffDef+AM_ToxicBuildup.stages.moderate.label | G83: 진행됨 | H83: =IF(ISERROR(E83),"",MATCH(F83,'240721'!$A$2:$A$2763,0)) -> 70
A84: HediffDef+AM_ToxicBuildup.stages.4.label | B84: HediffDef | D84: serious | E84: HediffDef+AM_ToxicBuildup.stages.serious.label | F84: =IF(E84="",IF(C84="",A84,C84),E84) -> HediffDef+AM_ToxicBuildup.stages.serious.label | G84: 심각함 | H84: =IF(ISERROR(E84),"",MATCH(F84,'240721'!$A$2:$A$2763,0)) -> 71
A85: HediffDef+AM_ToxicBuildup.stages.5.label | B85: HediffDef | D85: extreme | E85: HediffDef+AM_ToxicBuildup.stages.extreme.label | F85: =IF(E85="",IF(C85="",A85,C85),E85) -> HediffDef+AM_ToxicBuildup.stages.extreme.label | G85: 극심함 | H85: =IF(ISERROR(E85),"",MATCH(F85,'240721'!$A$2:$A$2763,0)) -> 72
A86: HediffDef+AM_Kamikaze.label | B86: HediffDef | D86: sudden detonation | F86: =IF(E86="",IF(C86="",A86,C86),E86) -> HediffDef+AM_Kamikaze.label | G86: 갑작스러운 폭발 | H86: =IF(ISERROR(E86),"",MATCH(F86,'240721'!$A$2:$A$2763,0)) -> 73
A87: HediffDef+AM_Kamikaze.description | B87: HediffDef | D87: Boom. | F87: =IF(E87="",IF(C87="",A87,C87),E87) -> HediffDef+AM_Kamikaze.description | G87: 폭발합니다. | H87: =IF(ISERROR(E87),"",MATCH(F87,'240721'!$A$2:$A$2763,0)) -> 74
A88: HediffDef+AM_Kamikaze.stages.0.label | B88: HediffDef | D88: initial-hidden | E88: HediffDef+AM_Kamikaze.stages.initialhidden.label | F88: =IF(E88="",IF(C88="",A88,C88),E88) -> HediffDef+AM_Kamikaze.stages.initialhidden.label | G88: 초기-숨겨짐 | H88: =IF(ISERROR(E88),"",MATCH(F88,'240721'!$A$2:$A$2763,0)) -> 75
A89: HediffDef+AM_Kamikaze.stages.1.label | B89: HediffDef | D89: critical | E89: HediffDef+AM_Kamikaze.stages.critical.label | F89: =IF(E89="",IF(C89="",A89,C89),E89) -> HediffDef+AM_Kamikaze.stages.critical.label | G89: 폭발 직전 | H89: =IF(ISERROR(E89),"",MATCH(F89,'240721'!$A$2:$A$2763,0)) -> 76
A90: HistoryEventDef+AM_DespisedAnimalDied.label | B90: HistoryEventDef | D90: despised animal died | F90: =IF(E90="",IF(C90="",A90,C90),E90) -> HistoryEventDef+AM_DespisedAnimalDied.label | G90: 멸시받는 동물이 죽음 | H90: =IF(ISERROR(E90),"",MATCH(F90,'240721'!$A$2:$A$2763,0)) -> 778
A91: HistoryEventDef+AM_AnimalDied.label | B91: HistoryEventDef | D91: animal died | F91: =IF(E91="",IF(C91="",A91,C91),E91) -> HistoryEventDef+AM_AnimalDied.label | G91: 동물이 죽음 | H91: =IF(ISERROR(E91),"",MATCH(F91,'240721'!$A$2:$A$2763,0)) -> 779
A92: HistoryEventDef+AM_AnimalReleased.label | B92: HistoryEventDef | D92: animal released | F92: =IF(E92="",IF(C92="",A92,C92),E92) -> HistoryEventDef+AM_AnimalReleased.label | G92: 가축을 해방함 | H92: =IF(ISERROR(E92),"",MATCH(F92,'240721'!$A$2:$A$2763,0)) -> 819
A93: HistoryEventDef+AM_TameAnimal.label | B93: HistoryEventDef | D93: taming animal | F93: =IF(E93="",IF(C93="",A93,C93),E93) -> HistoryEventDef+AM_TameAnimal.label | G93: 동물을 길들임 | H93: =IF(ISERROR(E93),"",MATCH(F93,'240721'!$A$2:$A$2763,0)) -> 913
A94: HistoryEventDef+AM_TrainAnimal.label | B94: HistoryEventDef | D94: training animal | F94: =IF(E94="",IF(C94="",A94,C94),E94) -> HistoryEventDef+AM_TrainAnimal.label | G94: 동물을 훈련시킴 | H94: =IF(ISERROR(E94),"",MATCH(F94,'240721'!$A$2:$A$2763,0)) -> 914
A95: HistoryEventDef+AM_UsedMelee.label | B95: HistoryEventDef | D95: used non-ranged attack | F95: =IF(E95="",IF(C95="",A95,C95),E95) -> HistoryEventDef+AM_UsedMelee.label | G95: 원거리가 아닌 공격을 함 | H95: =IF(ISERROR(E95),"",MATCH(F95,'240721'!$A$2:$A$2763,0)) -> 918
A96: HistoryEventDef+AM_UsedRanged.label | B96: HistoryEventDef | D96: used ranged attack | F96: =IF(E96="",IF(C96="",A96,C96),E96) -> HistoryEventDef+AM_UsedRanged.label | G96: 원거리 공격을 함 | H96: =IF(ISERROR(E96),"",MATCH(F96,'240721'!$A$2:$A$2763,0)) -> 919
A97: HistoryEventDef+AM_HarvestedNonColonistOrgan.label | B97: HistoryEventDef | D97: harvested non-colonist organ | F97: =IF(E97="",IF(C97="",A97,C97),E97) -> HistoryEventDef+AM_HarvestedNonColonistOrgan.label | G97: 정착민이 아닌 누군가의 장기를 적출함 | H97: =IF(ISERROR(E97),"",MATCH(F97,'240721'!$A$2:$A$2763,0)) -> 983
A98: HistoryEventDef+AM_BuildingReliquary.label | B98: HistoryEventDef | D98: building a reliquary | F98: =IF(E98="",IF(C98="",A98,C98),E98) -> HistoryEventDef+AM_BuildingReliquary.label | G98: 성물함을 지음 | H98: =IF(ISERROR(E98),"",MATCH(F98,'240721'!$A$2:$A$2763,0)) -> 1018
A99: HistoryEventDef+AM_SomeoneDied.label | B99: HistoryEventDef | D99: someone died | F99: =IF(E99="",IF(C99="",A99,C99),E99) -> HistoryEventDef+AM_SomeoneDied.label | G99: 누군가가 죽음 | H99: =IF(ISERROR(E99),"",MATCH(F99,'240721'!$A$2:$A$2763,0)) -> 937
A100: HistoryEventDef+AM_BoughtPrefabOnMerchant.label | B100: HistoryEventDef | D100: bought prefab on trader | F100: =IF(E100="",IF(C100="",A100,C100),E100) -> HistoryEventDef+AM_BoughtPrefabOnMerchant.label | G100: 상단에게 조립식 설계도를 구매함 | H100: =IF(ISERROR(E100),"",MATCH(F100,'240721'!$A$2:$A$2763,0)) -> 2645
A101: IdeoStoryPatternDef+AM_AtheismDescription.rules.rulesStrings.0 | B101: IdeoStoryPatternDef | D101: lesson(priority=-1)->stuff happens | F101: =IF(E101="",IF(C101="",A101,C101),E101) -> IdeoStoryPatternDef+AM_AtheismDescription.rules.rulesStrings.0 | G101: lesson(priority=-1)->일어날 일은 일어난다는 것을 | H101: =IF(ISERROR(E101),"",MATCH(F101,'240721'!$A$2:$A$2763,0)) -> 1088
... A2070: ThingDef+AM_Pyramid.description | B2070: ThingDef | D2070: A gigantic stone structure whose outer surfaces are triangular and converge to a single step at the top. | F2070: =IF(E2070="",IF(C2070="",A2070,C2070),E2070) -> ThingDef+AM_Pyramid.description | G2070: 외부 면이 삼각형 모양이고 꼭대기에서 한점으로 모이는 거대한 석조 건축물입니다. | H2070: =IF(ISERROR(E2070),"",MATCH(F2070,'240721'!$A$2:$A$2763,0)) -> 1455
A2071: ThingDef+AM_Pyramid.comps.0.inspectString | B2071: ThingDef | D2071: Contains the remains of: {CORPSES} | E2071: ThingDef+AM_Pyramid.comps.Comp_CorpseContainer.inspectString | F2071: =IF(E2071="",IF(C2071="",A2071,C2071),E2071) -> ThingDef+AM_Pyramid.comps.Comp_CorpseContainer.inspectString | G2071: 들어있는 시체: {CORPSES} | H2071: =IF(ISERROR(E2071),"",MATCH(F2071,'240721'!$A$2:$A$2763,0)) -> 1456
A2072: ThingDef+AM_GrandGate.label | B2072: ThingDef | D2072: grand gate | F2072: =IF(E2072="",IF(C2072="",A2072,C2072),E2072) -> ThingDef+AM_GrandGate.label | G2072: 장엄한 문 | H2072: =IF(ISERROR(E2072),"",MATCH(F2072,'240721'!$A$2:$A$2763,0)) -> 1457
A2073: ThingDef+AM_GrandGate.description | B2073: ThingDef | D2073: A huge entrance for a kemetic city. | F2073: =IF(E2073="",IF(C2073="",A2073,C2073),E2073) -> ThingDef+AM_GrandGate.description | G2073: 이집트 도시를 위한 거대한 출입구입니다. | H2073: =IF(ISERROR(E2073),"",MATCH(F2073,'240721'!$A$2:$A$2763,0)) -> 1458
A2074: ThingDef+AM_FuturisticObelisk.label | B2074: ThingDef | D2074: futuristic obelisk | F2074: =IF(E2074="",IF(C2074="",A2074,C2074),E2074) -> ThingDef+AM_FuturisticObelisk.label | G2074: 미래형 오벨리스크 | H2074: =IF(ISERROR(E2074),"",MATCH(F2074,'240721'!$A$2:$A$2763,0)) -> 1459
A2075: ThingDef+AM_FuturisticObelisk.description | B2075: ThingDef | D2075: A huge metallic obelisk. | F2075: =IF(E2075="",IF(C2075="",A2075,C2075),E2075) -> ThingDef+AM_FuturisticObelisk.description | G2075: 거대한 금속 오벨리스크입니다. | H2075: =IF(ISERROR(E2075),"",MATCH(F2075,'240721'!$A$2:$A$2763,0)) -> 1460
A2076: ThingDef+AM_FuturisticStele.label | B2076: ThingDef | D2076: futuristic stele | F2076: =IF(E2076="",IF(C2076="",A2076,C2076),E2076) -> ThingDef+AM_FuturisticStele.label | G2076: 미래형 비석 | H2076: =IF(ISERROR(E2076),"",MATCH(F2076,'240721'!$A$2:$A$2763,0)) -> 1461
A2077: ThingDef+AM_FuturisticStele.description | B2077: ThingDef | D2077: A huge metallic stele. | F2077: =IF(E2077="",IF(C2077="",A2077,C2077),E2077) -> ThingDef+AM_FuturisticStele.description | G2077: 거대한 금속 비석입니다. | H2077: =IF(ISERROR(E2077),"",MATCH(F2077,'240721'!$A$2:$A$2763,0)) -> 1462
A2078: ThingDef+AM_FuturisticPyramid.label | B2078: ThingDef | D2078: futuristic great pyramid | F2078: =IF(E2078="",IF(C2078="",A2078,C2078),E2078) -> ThingDef+AM_FuturisticPyramid.label | G2078: 미래형 거대한 피라미드 | H2078: =IF(ISERROR(E2078),"",MATCH(F2078,'240721'!$A$2:$A$2763,0)) -> 1463
A2079: ThingDef+AM_FuturisticPyramid.description | B2079: ThingDef | D2079: A truly colossal metallic structure whose outer surfaces are triangular and converge to a single step at the top. | F2079: =IF(E2079="",IF(C2079="",A2079,C2079),E2079) -> ThingDef+AM_FuturisticPyramid.description | G2079: 외부 면이 삼각형 모양이고 꼭대기에서 한점으로 모이는 엄청나게 거대한 금속 건축물입니다. | H2079: =IF(ISERROR(E2079),"",MATCH(F2079,'240721'!$A$2:$A$2763,0)) -> 1464
A2080: ThingDef+AM_FuturisticPyramid.comps.3.inspectString | B2080: ThingDef | D2080: Contains the last remains of {CORPSE} | E2080: ThingDef+AM_FuturisticPyramid.comps.Comp_CorpseContainer.inspectString | F2080: =IF(E2080="",IF(C2080="",A2080,C2080),E2080) -> ThingDef+AM_FuturisticPyramid.comps.Comp_CorpseContainer.inspectString | G2080: {CORPSE}의 시체가 들어있습니다 | H2080: =IF(ISERROR(E2080),"",MATCH(F2080,'240721'!$A$2:$A$2763,0)) -> 1465
A2081: ThingDef+AM_GreatPyramid.label | B2081: ThingDef | D2081: great pyramid | F2081: =IF(E2081="",IF(C2081="",A2081,C2081),E2081) -> ThingDef+AM_GreatPyramid.label | G2081: 거대한 피라미드 | H2081: =IF(ISERROR(E2081),"",MATCH(F2081,'240721'!$A$2:$A$2763,0)) -> 1466
A2082: ThingDef+AM_GreatPyramid.description | B2082: ThingDef | D2082: A truly colossal stone structure whose outer surfaces are triangular and converge to a single step at the top. | F2082: =IF(E2082="",IF(C2082="",A2082,C2082),E2082) -> ThingDef+AM_GreatPyramid.description | G2082: 외부 면이 삼각형 모양이고 꼭대기에서 한점으로 모이는 엄청나게 거대한 석조 건축물입니다. | H2082: =IF(ISERROR(E2082),"",MATCH(F2082,'240721'!$A$2:$A$2763,0)) -> 1467
A2083: ThingDef+AM_GreatPyramid.comps.3.inspectString | B2083: ThingDef | D2083: Contains the last remains of {CORPSE} | E2083: ThingDef+AM_GreatPyramid.comps.Comp_CorpseContainer.inspectString | F2083: =IF(E2083="",IF(C2083="",A2083,C2083),E2083) -> ThingDef+AM_GreatPyramid.comps.Comp_CorpseContainer.inspectString | G2083: {CORPSE}의 시체가 들어있습니다 | H2083: =IF(ISERROR(E2083),"",MATCH(F2083,'240721'!$A$2:$A$2763,0)) -> 1468
A2084: ThingDef+AM_Sphynx.label | B2084: ThingDef | D2084: sphinx | F2084: =IF(E2084="",IF(C2084="",A2084,C2084),E2084) -> ThingDef+AM_Sphynx.label | G2084: 스핑크스 | H2084: =IF(ISERROR(E2084),"",MATCH(F2084,'240721'!$A$2:$A$2763,0)) -> 1469
A2085: ThingDef+AM_Sphynx.description | B2085: ThingDef | D2085: A truly colossal statue of a sphinx, a mythical creature with the head of a human, and the body of a lion. | F2085: =IF(E2085="",IF(C2085="",A2085,C2085),E2085) -> ThingDef+AM_Sphynx.description | G2085: 인간의 머리와 사자의 몸을 가진 신화 속 생물인 스핑크스를 묘사한 엄청나게 거대한 조각상입니다. | H2085: =IF(ISERROR(E2085),"",MATCH(F2085,'240721'!$A$2:$A$2763,0)) -> 1470
A2086: ThingDef+AM_Megalith.label | B2086: ThingDef | D2086: megalith | F2086: =IF(E2086="",IF(C2086="",A2086,C2086),E2086) -> ThingDef+AM_Megalith.label | G2086: 거석 기념물 | H2086: =IF(ISERROR(E2086),"",MATCH(F2086,'240721'!$A$2:$A$2763,0)) -> 1471
A2087: ThingDef+AM_Megalith.description | B2087: ThingDef | D2087: A large stone used to construct a prehistoric structure or monument, either alone or together with other stones, often hewn in definite shapes for special purposes. | F2087: =IF(E2087="",IF(C2087="",A2087,C2087),E2087) -> ThingDef+AM_Megalith.description | G2087: 선사 시대에 건축물이나 기념물을 건설하기 위해 하나 또는 여러 개가 사용된 큰 돌입니다. 특별한 목적을 위해 정해진 모양으로 다듬기도 합니다. | H2087: =IF(ISERROR(E2087),"",MATCH(F2087,'240721'!$A$2:$A$2763,0)) -> 1472
A2088: ThingDef+AM_StoneBedroll.label | B2088: ThingDef | D2088: stone-framed bedroll | F2088: =IF(E2088="",IF(C2088="",A2088,C2088),E2088) -> ThingDef+AM_StoneBedroll.label | G2088: 돌 뼈대 침낭 | H2088: =IF(ISERROR(E2088),"",MATCH(F2088,'240721'!$A$2:$A$2763,0)) -> 1473
A2089: ThingDef+AM_StoneBedroll.description | B2089: ThingDef | D2089: A cozy mattress and sheets on a frame for resting. | F2089: =IF(E2089="",IF(C2089="",A2089,C2089),E2089) -> ThingDef+AM_StoneBedroll.description | G2089: 아늑한 매트리스와 천으로 덮여있는 침대입니다. | H2089: =IF(ISERROR(E2089),"",MATCH(F2089,'240721'!$A$2:$A$2763,0)) -> 1474
A2090: ThingDef+AM_AncientBed.label | B2090: ThingDef | D2090: restored ancient bed | F2090: =IF(E2090="",IF(C2090="",A2090,C2090),E2090) -> ThingDef+AM_AncientBed.label | G2090: 복원된 고대 침대 | H2090: =IF(ISERROR(E2090),"",MATCH(F2090,'240721'!$A$2:$A$2763,0)) -> 1477
A2091: ThingDef+AM_AncientBed.description | B2091: ThingDef | D2091: An old, rotted mattress on a rusty frame. Restored to be useable, though a bit uncomfortable. | F2091: =IF(E2091="",IF(C2091="",A2091,C2091),E2091) -> ThingDef+AM_AncientBed.description | G2091: 녹슨 침대 프레임과 낡고 문드러진 매트리스입니다. 조금 불편해도 사용할 수 있도록 복원되었습니다. | H2091: =IF(ISERROR(E2091),"",MATCH(F2091,'240721'!$A$2:$A$2763,0)) -> 1478
A2092: ThingDef+AM_AncientDoubleBed.label | B2092: ThingDef | D2092: restored ancient double bed | F2092: =IF(E2092="",IF(C2092="",A2092,C2092),E2092) -> ThingDef+AM_AncientDoubleBed.label | G2092: 복원된 고대 큰 침대 | H2092: =IF(ISERROR(E2092),"",MATCH(F2092,'240721'!$A$2:$A$2763,0)) -> 1479
A2093: ThingDef+AM_AncientDoubleBed.description | B2093: ThingDef | D2093: An old, rotted mattress on a rusty frame. Restored to be useable, though a bit uncomfortable. Fits two people. | F2093: =IF(E2093="",IF(C2093="",A2093,C2093),E2093) -> ThingDef+AM_AncientDoubleBed.description | G2093: 녹슨 침대 프레임과 낡고 문드러진 매트리스입니다. 조금 불편해도 사용할 수 있도록 복원되었습니다. 두 명이 누울 수 있습니다. | H2093: =IF(ISERROR(E2093),"",MATCH(F2093,'240721'!$A$2:$A$2763,0)) -> 1480
A2094: ThingDef+AM_AncientOperatingTable.label | B2094: ThingDef | D2094: restored ancient operating table | F2094: =IF(E2094="",IF(C2094="",A2094,C2094),E2094) -> ThingDef+AM_AncientOperatingTable.label | G2094: 복원된 고대 수술대 | H2094: =IF(ISERROR(E2094),"",MATCH(F2094,'240721'!$A$2:$A$2763,0)) -> 1481
A2095: ThingDef+AM_AncientOperatingTable.description | B2095: ThingDef | D2095: An ancient bed once used for forgotten surgical operations. Adjustable for a patient and festooned with built-in equipment, it improves medical outcomes over normal beds. Uncomfortable but efficient. | F2095: =IF(E2095="",IF(C2095="",A2095,C2095),E2095) -> ThingDef+AM_AncientOperatingTable.description | G2095: 오래 전 수술 작업에 사용되었을 고대 침대입니다. 환자에게 맞게 조정이 가능하고 장비가 내장되어 있어 일반 침대보다 의료 결과가 향상됩니다. 불편하지만 효율적입니다. | H2095: =IF(ISERROR(E2095),"",MATCH(F2095,'240721'!$A$2:$A$2763,0)) -> 1482
... A2160: ThingDef+AM_UnshackledDryad.description | B2160: ThingDef | D2160: Dryads are small mammalian creatures that have a symbiotic relationship with the Gauranlen tree.\n\nThis particular dryad seems to be unshackled, and it will not leave the region if no Gauranlen trees are around. It seems to be bound to the colonists. | F2160: =IF(E2160="",IF(C2160="",A2160,C2160),E2160) -> ThingDef+AM_UnshackledDryad.description | G2160: 나무지기는 요정나무와 공생관계를 이루는 작은 포유동물입니다.\n\n이 특별한 나무지기는 묶여있지 않은 것처럼 보이며, 주변에 요정나무가 없다면 이 지역을 떠나지 않을 것입니다. 이 나무지기는 정착민에게 묶여있는 것처럼 보입니다. | H2160: =IF(ISERROR(E2160),"",MATCH(F2160,'240721'!$A$2:$A$2763,0)) -> 1607
A2161: ThingDef+AM_UnshackledDryad.tools.0.label | B2161: ThingDef | D2161: left claw | E2161: ThingDef+AM_UnshackledDryad.tools.left_claw.label | F2161: =IF(E2161="",IF(C2161="",A2161,C2161),E2161) -> ThingDef+AM_UnshackledDryad.tools.left_claw.label | G2161: 왼쪽 발톱 | H2161: =IF(ISERROR(E2161),"",MATCH(F2161,'240721'!$A$2:$A$2763,0)) -> 1608
A2162: ThingDef+AM_UnshackledDryad.tools.1.label | B2162: ThingDef | D2162: right claw | E2162: ThingDef+AM_UnshackledDryad.tools.right_claw.label | F2162: =IF(E2162="",IF(C2162="",A2162,C2162),E2162) -> ThingDef+AM_UnshackledDryad.tools.right_claw.label | G2162: 오른쪽 발톱 | H2162: =IF(ISERROR(E2162),"",MATCH(F2162,'240721'!$A$2:$A$2763,0)) -> 1609
A2163: ThingDef+AM_UnshackledDryad.tools.3.label | B2163: ThingDef | D2163: head | E2163: ThingDef+AM_UnshackledDryad.tools.head.label | F2163: =IF(E2163="",IF(C2163="",A2163,C2163),E2163) -> ThingDef+AM_UnshackledDryad.tools.head.label | G2163: 머리 | H2163: =IF(ISERROR(E2163),"",MATCH(F2163,'240721'!$A$2:$A$2763,0)) -> 1610
A2164: ThingDef+AM_DoubleStoneBedroll.label | B2164: ThingDef | D2164: double stone-framed bedroll | F2164: =IF(E2164="",IF(C2164="",A2164,C2164),E2164) -> ThingDef+AM_DoubleStoneBedroll.label | G2164: 큰 돌침대 | H2164: =IF(ISERROR(E2164),"",MATCH(F2164,'240721'!$A$2:$A$2763,0)) -> 1475
A2165: ThingDef+AM_DoubleStoneBedroll.description | B2165: ThingDef | D2165: A cozy mattress and sheets on a frame for resting. | F2165: =IF(E2165="",IF(C2165="",A2165,C2165),E2165) -> ThingDef+AM_DoubleStoneBedroll.description | G2165: 석재 뼈대 위에 아늑한 매트리스와 시트가 있습니다. | H2165: =IF(ISERROR(E2165),"",MATCH(F2165,'240721'!$A$2:$A$2763,0)) -> 1476
A2166: ThingDef+AM_CorruptedGaumakerCocoon.label | B2166: ThingDef | D2166: corrupted pod | F2166: =IF(E2166="",IF(C2166="",A2166,C2166),E2166) -> ThingDef+AM_CorruptedGaumakerCocoon.label | G2166: 부패단지 고치 | H2166: =IF(ISERROR(E2166),"",MATCH(F2166,'240721'!$A$2:$A$2763,0)) -> 1507
A2167: ThingDef+AM_CorruptedGaumakerCocoon.description | B2167: ThingDef | D2167: The result of the merging of several Corruptor dryads, this symbiotic plant/animal pod is an essential part of the corrupted Gauranlen life cycle. After some time, it will flower into a mature Gauranlen pod which can be harvested to plant a new Gauranlen tree. | F2167: =IF(E2167="",IF(C2167="",A2167,C2167),E2167) -> ThingDef+AM_CorruptedGaumakerCocoon.description | G2167: 여러 부패단지 나무지기의 융합체. 이 고치는 부패한 요정나무의 생명 주기에서 가장 중요한 부분입니다. 시간이 지나면 이곳에 돋아난 부패열매를 수확하여 부패한 요정나무를 키워낼 수 있을 겁니다. | H2167: =IF(ISERROR(E2167),"",MATCH(F2167,'240721'!$A$2:$A$2763,0)) -> 1508
A2168: ThingDef+AM_PoisonBolt.label | B2168: ThingDef | D2168: venomous spit | F2168: =IF(E2168="",IF(C2168="",A2168,C2168),E2168) -> ThingDef+AM_PoisonBolt.label | G2168: 독침 | H2168: =IF(ISERROR(E2168),"",MATCH(F2168,'240721'!$A$2:$A$2763,0)) -> 1515
A2169: ThingDef+AM_Apparel_Eyepatch.label | B2169: ThingDef | D2169: eyepatch | F2169: =IF(E2169="",IF(C2169="",A2169,C2169),E2169) -> ThingDef+AM_Apparel_Eyepatch.label | G2169: 눈가리개 | H2169: =IF(ISERROR(E2169),"",MATCH(F2169,'240721'!$A$2:$A$2763,0)) -> 1516
A2170: ThingDef+AM_Apparel_Eyepatch.description | B2170: ThingDef | D2170: A protective covering, usually made of cloth, for an injured eye. Or just for style. | F2170: =IF(E2170="",IF(C2170="",A2170,C2170),E2170) -> ThingDef+AM_Apparel_Eyepatch.description | G2170: 다친 눈을 보호하기 위한 천입니다. 또는 스타일을 위해 사용하기도 합니다. | H2170: =IF(ISERROR(E2170),"",MATCH(F2170,'240721'!$A$2:$A$2763,0)) -> 1517
A2171: ThingDef+AM_Filth_RedSlime.label | B2171: ThingDef | D2171: red slime | F2171: =IF(E2171="",IF(C2171="",A2171,C2171),E2171) -> ThingDef+AM_Filth_RedSlime.label | G2171: 붉은 슬라임 | H2171: =IF(ISERROR(E2171),"",MATCH(F2171,'240721'!$A$2:$A$2763,0)) -> 1558
A2172: ThingDef+AM_Filth_OcularGoo.label | B2172: ThingDef | D2172: ocular goo | F2172: =IF(E2172="",IF(C2172="",A2172,C2172),E2172) -> ThingDef+AM_Filth_OcularGoo.label | G2172: 눈알 액체괴물 | H2172: =IF(ISERROR(E2172),"",MATCH(F2172,'240721'!$A$2:$A$2763,0)) -> 1559
A2173: ThingDef+GU_RedWood.label | B2173: ThingDef | D2173: red wood | F2173: =IF(E2173="",IF(C2173="",A2173,C2173),E2173) -> ThingDef+GU_RedWood.label | G2173: 붉은 나무 | H2173: =IF(ISERROR(E2173),"",MATCH(F2173,'240721'!$A$2:$A$2763,0)) -> 1560
A2174: ThingDef+GU_RedWood.description | B2174: ThingDef | D2174: This red tinged wood is oddly strong, and a sweet scent emanates from it. Less flammable than terrestrial wood, but quite ugly. | F2174: =IF(E2174="",IF(C2174="",A2174,C2174),E2174) -> ThingDef+GU_RedWood.description | G2174: 이 붉은빛의 나무는 이상하리만큼 강하고 달콤한 향기가 납니다. 지상의 목재보다 가연성이 적지만 보기 흉합니다. | H2174: =IF(ISERROR(E2174),"",MATCH(F2174,'240721'!$A$2:$A$2763,0)) -> 1561
A2175: ThingDef+GU_RedWood.stuffProps.stuffAdjective | B2175: ThingDef | D2175: red wooden | F2175: =IF(E2175="",IF(C2175="",A2175,C2175),E2175) -> ThingDef+GU_RedWood.stuffProps.stuffAdjective | G2175: 붉은 나무 | H2175: =IF(ISERROR(E2175),"",MATCH(F2175,'240721'!$A$2:$A$2763,0)) -> 1562
A2176: ThingDef+GU_RedWood.tools.0.label | B2176: ThingDef | D2176: red wood log | E2176: ThingDef+GU_RedWood.tools.red_wood_log.label | F2176: =IF(E2176="",IF(C2176="",A2176,C2176),E2176) -> ThingDef+GU_RedWood.tools.red_wood_log.label | G2176: 붉은 통나무 | H2176: =IF(ISERROR(E2176),"",MATCH(F2176,'240721'!$A$2:$A$2763,0)) -> 1563
A2177: ThingDef+AM_Plant_CorruptedPodGauranlen.label | B2177: ThingDef | D2177: corrupted Gauranlen pod | F2177: =IF(E2177="",IF(C2177="",A2177,C2177),E2177) -> ThingDef+AM_Plant_CorruptedPodGauranlen.label | G2177: 부패열매 | H2177: =IF(ISERROR(E2177),"",MATCH(F2177,'240721'!$A$2:$A$2763,0)) -> 1567
A2178: ThingDef+AM_Plant_CorruptedPodGauranlen.description | B2178: ThingDef | D2178: A small pod that protects a single corrupted Gauranlen seed. This seed can be harvested and used to plant a Gauranlen tree. | F2178: =IF(E2178="",IF(C2178="",A2178,C2178),E2178) -> ThingDef+AM_Plant_CorruptedPodGauranlen.description | G2178: 안에 들어있는 부패씨앗을 보호하는 작은 꼬투리입니다. 안에 씨앗을 채집해 부패한 요정나무를 심을 수 있습니다. | H2178: =IF(ISERROR(E2178),"",MATCH(F2178,'240721'!$A$2:$A$2763,0)) -> 1568
...
